Workbook

Sheet Summary
A1: TP Mandarin Landing Pages (MLP) - Translation Review Document
B2: 14
A3: Field | B3: =SUM(C9:C22) -> 882
A4: Project Name | B4: =SUM(C8:C13) -> 250
A5: Document Version | B5: v1.0
A6: Total Pages | B6: 6 (index, about-tp, area-around-office, casual-interview, cost-of-living, daily-life-malaysia)
A7: Translator | B7: Claude AI
A8: Total Pages | B8: 14 (about-tp.html area-around-office.html casual-interview.html cost-of-living.html daily-life-malaysia.html hiring-process.html index.html office-environment.html open-jobs.html relocation-visa.html salary-and-benefits.html ta-team.html testimonials.html | C8: Column1 | D8: Column2
A9: about-tp.html | B9: https://tpmyandtpth.github.io/MLP/about-tp.html | C9: 19 | D9: ⬜ Pending
A10: area-around-office.html | B10: https://tpmyandtpth.github.io/MLP/area-around-office.html | C10: 27 | D10: ⬜ Pending
A11: casual-interview.html | B11: https://tpmyandtpth.github.io/MLP/casual-interview.html | C11: 62 | D11: ⬜ Pending
A12: cost-of-living.html | B12: https://tpmyandtpth.github.io/MLP/cost-of-living.html | C12: 36 | D12: ⬜ Pending
A13: daily-life-malaysia.html | B13: https://tpmyandtpth.github.io/MLP/daily-life-malaysia.html | C13: 106 | D13: ⬜ Pending
A14: hiring-process.html | B14: https://tpmyandtpth.github.io/MLP/hiring-process.html | C14: 49 | D14: ⬜ Pending
A15: index.html | B15: https://tpmyandtpth.github.io/MLP/index.html | C15: 112 | D15: Done
A16: office-environment.html | B16: https://tpmyandtpth.github.io/MLP/office-environment.html | C16: 89 | D16: ⬜ Pending
A17: open-jobs.html | B17: https://tpmyandtpth.github.io/MLP/open-jobs.html | C17: 62 | D17: ⬜ Pending
A18: relocation-visa.html | B18: https://tpmyandtpth.github.io/MLP/relocation-visa.html | C18: 68 | D18: ⬜ Pending
A19: salary-and-benefits.html | B19: https://tpmyandtpth.github.io/MLP/salary-and-benefits.html | C19: 57 | D19: ⬜ Pending
A20: ta-team.html | B20: https://tpmyandtpth.github.io/MLP/ta-team.html | C20: 78 | D20: ⬜ Pending
... A22: why-malaysia-thailand.html | B22: https://tpmyandtpth.github.io/MLP/why-malaysia-thailand.html | C22: 68 | D22: ⬜ Pending

Sheet index.html
A1: Field | B1: Value
A2: Page URL | B2: https://tpmyandtpth.github.io/MLP/index.html
A3: Page Title (EN) | B3: Homepage / Landing Page
A4: Page Title (CN) | B4: TP招聘 | 马来西亚·泰国华语工作机会 | C4: TP招聘 | 马来西亚·泰国中文工作机会
A5: Created Date | B5: 2026-01-27
A6: Translator | B6: Claude AI
A7: Review Date | B7: 46064
A8: Reviewer Name | B8: Anna Saw
A9: Review Status | B9: Completed
A10: Version | B10: v1.0
A13: Content Review Table
A15: Line # | B15: Section | C15: Local Mandarin (Mixed English) | D15: Local Comment | E15: Native Mandarin | F15: Native Comment
A16: 35 | B16: Lang Toggle | C16: 🇲🇾 本地华人 | E16: 🇲🇾 本地华人
A17: 36 | B17: Lang Toggle | C17: 🌏 海外华人 | E17: 🌏 海外华人
A18: 57 | B18: Header Nav | C18: Open Jobs | D18: 在招职位 | E18: 职位列表
A19: 59 | B19: Header Nav | C19: 薪资·Benefits | D19: 薪资福利 | E19: 薪资福利
A20: 61 | B20: Header Nav | C20: 为什么选择MY/TH | D20: 为什么选择马来西亚和泰国 | E20: 为什么选择马来西亚和泰国
A21: 62 | B21: Header Nav | C21: Visa·搬迁 | D21: 签证与搬迁安排 | E21: 签证·搬迁 | F21: 签证与搬迁支持
A22: 63 | B22: Header Nav | C22: Apply Now | D22: 立即申请 | E22: 立即申请
A23: 83 | B23: Hero Typewriter | C23: 用华语，开启Global Career | D23: 用华语，开启国际职涯 | E23: 用华语，开启全球化职业生涯
A24: 84 | B24: Hero Typewriter | C24: 在东南亚，体验理想Life | D24: 在东南亚，体验理想生活 | E24: 在东南亚，体验理想生活
A25: 85 | B25: Hero Typewriter | C25: 加入世界500强BPO企业 | E25: 加入世界500强业务流程外包企业
A26: 93 | B26: Hero Subtitle | C26: 你的下一个Career，从这里开始 | D26: 你的下一份工作，从这里开始 | E26: 你的下一份事业，从这里开始
A27: 97 | B27: Hero CTA | C27: 查看Open Jobs | D27: 查看在招职位 | E27: 查看职位
A28: 101 | B28: Hero Stats | C28: 国家/地区 | E28: 运营国家
A29: 102 | B29: Hero Stats | C29: 全球Employee | D29: 全球员工规模 | E29: 全球员工 | F29: 全球员工规模
A30: 103 | B30: Hero Stats | C30: MY/TH员工 | D30: 马来西亚/泰国员工 | E30: 马来西亚/泰国员工
A31: 108 | B31: Social Proof | C31: 年连续Great Place to Work® | D31: 连续多年Great Place to Work® 认证 | E31: 年连续最佳职场认证 | F31: 连续多年荣获最佳职场认证
A32: 109 | B32: Social Proof | C32: 年World's Best Workplaces™ | D32: World's Best Workplaces™ 认证 | E32: 年全球最佳职场 | F32: 年度全球最佳职场
A33: 114 | B33: About Section | C33: 你的下一个Career从这里开始！ | D33: 你的下一份工作，从这里开始 | E33: 你的下一份事业从这里开始！
A34: 117 | B34: About Text | C34: TP是全球领先的BPO（Business Process Outsourcing）企业 | E34: TP是全球领先的业务流程外包企业
A35: 118 | B35: About Text | C35: 为全球知名Brand提供卓越的Customer Experience服务 | D35: 为国际知名品牌提供客户体验服务 | E35: 为全球知名品牌提供卓越的客户体验服务
A36: 119 | B36: About Text | C36: 无论你是Fresh Graduate还是经验丰富的Professional | D36: 无论你是Fresh Graduate还是有工作经验 | E36: 无论你是应届毕业生还是经验丰富的专业人士
A37: 128 | B37: GPTW Section | C37: TP 荣获 Great Place to Work® 评选的「World's Best Workplaces™」 | E37: TP 荣获卓越职场研究机构评选的「全球最佳职场」
A38: 138 | B38: GPTW Description | C38: 基于员工的 Feedback 与信任...Empower 员工 | D38: 基于员工的 反馈与信任...支持员工成长与发展 | E38: 基于员工的反馈与信任...赋能员工 | F38: 基于员工的 反馈与信任...支持员工成长与发展
A39: 160 | B39: GPTW Stats | C39: 全球 Employee 人数 | D39: 全球员工人数 | E39: 全球员工人数
A40: 165 | B40: Chinese Community | C40: 华语Community在TP | D40: TP 中文员工社区 | E40: TP的华语社区 | F40: TP 中文员工社区
A41: 170 | B41: Community Stats | C41: WeChat Group | D41: WeChat 群组 | E41: 微信群组
A42: 177 | B42: Priority Menu | C42: 热门Topic | D42: 热门话题 | E42: 热门话题
A43: 182 | B43: Card | C43: 全球最大BPO企业之一 | E43: 全球最大业务流程外包企业之一
A44: 184 | B44: Card | C44: Open Jobs | D44: 在招职位 | E44: 职位列表
A45: 186 | B45: Card | C45: 薪资·Benefits | D45: 薪资福利 | E45: 薪资福利
A46: 188 | B46: Card | C46: Visa·搬迁Support | D46: 签证与搬迁协助 | E46: 签证·搬迁支持 | F46: 签证与搬迁协助
A47: 190 | B47: Card | C47: 员工Story | D47: 员工分享 | E47: 员工故事
A48: 192 | B48: Card | C48: 为什么选择MY/TH | D48: 为什么选择马来西亚或泰国 | E48: 为什么选择马来西亚和泰国 | F48: 为什么选择马来西亚或泰国
A49: 194 | B49: Card | C49: Casual面谈 | D49: 轻松交流 Interview | E49: 轻松面谈
A50: 196 | B50: Card | C50: 招聘Process | D50: 招聘流程 | E50: 招聘流程
A51: 197 | B51: Card | C51: Online完成全部流程 | D51: 全程 Online 完成 | E51: 在线完成全部流程 | F51: 全流程线上完成
A52: 199 | B52: Card | C52: 办公环境·Virtual Tour | E52: 办公环境·虚拟参观
A53: 200 | B53: Card | C53: 办公环境与Career Path | D53: 办公环境与发展机会 | E53: 办公环境与职业发展
A54: 202 | B54: Card | C54: 推荐 Bonus | E54: 推荐奖励
A55: 203 | B55: Card | C55: 推荐朋友获得 Reward | D55: 推荐朋友获得奖励 | E55: 推荐朋友获得奖励
A56: 205 | B56: Card | C56: Blog·最新消息 | E56: 博客·最新消息
A57: 214 | B57: Social Card | C57: WeChat微信 | E57: 微信
A58: 226 | B58: Icon Grid | C58: 生活信息·Support | D58: 生活资讯 · 支援 | E58: 生活信息·支持
A59: 227 | B59: Icon Grid | C59: 实用生活信息和 Resource | D59: 实用生活资讯和资源 | E59: 实用生活信息和资源
A60: 229 | B60: Icon Card | C60: MY 生活成本 | D60: 马来西亚生活成本 | E60: 马来西亚生活成本
A61: 231 | B61: Icon Card | C61: 招聘 Team 介绍 | D61: 招聘团队介绍 | E61: 招聘团队介绍
A62: 232 | B62: Icon Card | C62: 华语 Support | D62: 华语支援 | E62: 华语支持
A63: 234 | B63: Icon Card | C63: Office 周边 | D63: 办公室周边 | E63: 办公室周边
A64: 238 | B64: Icon Card | C64: Career Path·晋升 | D64: 职业发展·晋升 | E64: 职业发展·晋升
A65: 239 | B65: Icon Card | C65: 语言·Training Program | D65: 语言 · 培训课程 | E65: 语言·培训项目
A66: 241 | B66: Icon Card | C66: Event·企业文化 | D66: 活动 · 企业文化 | E66: 活动·企业文化
A67: 244 | B67: Icon Card | C67: 华语 Community | E67: 华语社区
A68: 248 | B68: Icon Card | C68: Onboarding 指南 | D68: 入职指南 | E68: 入职指南
A69: 250 | B69: Icon Card | C69: MY vs TH 对比 | D69: 马来西亚 vs 泰国 | E69: 马来西亚 vs 泰国
A70: 252 | B70: Icon Card | C70: Success Case | D70: 成功案例 | E70: 成功案例
A71: 256 | B71: Icon Card | C71: 家属 Visa | D71: 家属签证 | E71: 家属签证
A72: 258 | B72: Icon Card | C72: Remote Work | D72: 远程办公 | E72: 远程办公
A73: 259 | B73: Icon Card | C73: WFH Option | D73: 居家办公选项 | E73: 居家办公选项
A74: 261 | B74: Icon Card | C74: WeChat 官方账号 | E74: 微信官方账号
A75: 263 | B75: Icon Card | C75: LINE 官方 Account | D75: LINE 官方账号 | E75: LINE 官方账号
A76: 276 | B76: City Card | C76: 即将 Open | D76: 即将开放 | E76: 即将开放
A77: 283 | B77: Video Section | C77: 员工 Interview（视频） | E77: 员工访谈（视频）
A78: 284 | B78: Video Section | C78: 通过短视频了解真实的工作 Experience | D78: 通过短视频了解真实的工作体验 | E78: 通过短视频了解真实的工作体验
A79: 290 | B79: Video Card | C79: TP员工 Interview：Agent 篇 | E79: TP员工访谈：客服代表篇
A80: 291 | B80: Video Card | C80: 一线 Agent 的工作日常 | E80: 一线客服代表的工作日常
A81: 294 | B81: Video Card | C81: TP员工 Interview：Team Leader 篇 | E81: TP员工访谈：团队主管篇
A82: 295 | B82: Video Card | C82: 现场 Management 和培养的真实情况 | D82: 现场管理与人才培养的实际情况 | E82: 现场管理和人才培养的真实情况
A83: 298 | B83: Video Card | C83: TP员工 Interview：Operations Manager 篇 | E83: TP员工访谈：运营经理篇
A84: 299 | B84: Video Card | C84: Quality 和 Productivity 的幕后支持 | D84: 客服质量与绩效提升支持 | E84: 质量和生产力的幕后支持 | F84: 客服质量与绩效提升支持
A85: 304 | B85: World Map | C85: TP 全球 Network | D85: TP 全球网络布局 | E85: TP 全球网络
A86: 305 | B86: World Map | C86: 在 100 多个国家提供 Global Service | D86: 在 100 多个国家提供全球服务 | E86: 在 100 多个国家提供全球服务
A87: 312 | B87: Office Section | C87: 舒适且交通便利的 Workplace | D87: 舒适且交通便利的工作场所 | E87: 舒适且交通便利的工作场所
A88: 315 | B88: Office Card | C88: Ampang Park 站直达 | E88: 安邦公园站直达
A89: 316 | B89: Office Card | C89: KLCC 步行可达 | E89: 双子塔步行可达
A90: 317 | B90: Office Card | C90: Grade A Office Building | D90: Grade A 办公司楼 | E90: 甲级办公楼
A91: 321 | B91: Office Card | C91: 餐厅·Pharmacy nearby | D91: 餐厅·Pharmacy 附近 | E91: 餐厅·药房近在咫尺
A92: 325 | B92: Office Card | C92: Bayan Baru 区域 | E92: 峇央峇鲁区域
A93: 327 | B93: Office Card | C93: Queensbay Mall nearby | D93: Queensbay Mall 附近 | E93: 皇后湾广场附近
A94: 330 | B94: Office Card | C94: 州 GBS Hub | D94: 本州全球服务中心 | E94: 州全球商务服务中心
A95: 331 | B95: Office Card | C95: IT/BPO 集聚地 | E95: IT/业务流程外包集聚地
A96: 335 | B96: Office Card | C96: LRT 站附近 | E96: 轻轨站附近
A97: 336 | B97: Office Card | C97: Shopping 便利 | D97: 方便购物 | E97: 购物便利
A98: 339 | B98: Office Card | C98: BTS/MRT nearby | D98: BTS/MRT 附近 | E98: 轻轨/地铁附近
A99: 346 | B99: Office Card | C99: BRT 直达 | E99: 快速公交直达
A100: 355 | B100: Office Card | C100: WFH（居家办公） | E100: 居家办公
A101: 356 | B101: Office Card | C101: Remote Work Option | D101: 远程工作选项 | E101: 远程工作选项
A102: 361 | B102: Office CTA | C102: Virtual Office Tour → | E102: 虚拟办公室参观 →
A103: 366 | B103: Lifestyle | C103: 不只是工作充实的 Active Life | D103: 不只是工作充实的活力生活 | E103: 不只是工作充实的活力生活
...

Sheet about-tp.html
A1: Field | B1: Value
A2: Page URL | B2: https://tpmyandtpth.github.io/MLP/about-tp.html
A3: Page Title (EN) | B3: About TP
A4: Page Title (CN) | B4: 关于TP | TP招聘 马来西亚·泰国
A5: Created Date | B5: 2026-01-27
A6: Translator | B6: Claude AI
A7: Review Date | B7: 46064
A8: Reviewer Name | B8: Anna Saw
A9: Review Status | B9: Completed
A10: Version | B10: v1.0
A11: POC
A13: Content Review Table
A15: Line # | B15: Section | C15: Local Mandarin (Mixed English) | D15: Local Comment | E15: Native Mandarin | F15: Native Comment
A16: 287 | B16: Lang Toggle | C16: 🇲🇾 本地华人 | E16: 🇲🇾 本地华人
A17: 288 | B17: Lang Toggle | C17: 🌏 海外华人 | E17: 🌏 海外华人
A18: 292 | B18: Lang Dropdown | C18: Malaysian Chinese - 混合英文词汇 | D18: =IFERROR(_xlfn.XLOOKUP(C18,index.html!C:C,index.html!D:D)," ") | E18: Malaysian Chinese - 混合英文词汇
A19: 293 | B19: Lang Dropdown | C19: Expat Chinese - 纯中文版本 | D19: =IFERROR(_xlfn.XLOOKUP(C19,index.html!C:C,index.html!D:D)," ") | E19: Expat Chinese - 纯中文版本
A20: 310 | B20: Header Nav | C20: 薪资·Benefits | D20: =IFERROR(_xlfn.XLOOKUP(C20,index.html!C:C,index.html!D:D)," ") -> 薪资福利 | E20: 薪资福利
A21: 311 | B21: Header Nav | C21: 招聘Process | D21: =IFERROR(_xlfn.XLOOKUP(C21,index.html!C:C,index.html!D:D)," ") -> 招聘流程 | E21: 招聘流程
A22: 312 | B22: Header Nav | C22: 为什么选择MY/TH | D22: =IFERROR(_xlfn.XLOOKUP(C22,index.html!C:C,index.html!D:D)," ") -> 为什么选择马来西亚和泰国 | E22: 为什么选择马来西亚和泰国
A23: 313 | B23: Header Nav | C23: Visa·搬迁 | D23: =IFERROR(_xlfn.XLOOKUP(C23,index.html!C:C,index.html!D:D)," ") -> 签证与搬迁安排 | E23: 签证·搬迁 | F23: =IFERROR(_xlfn.XLOOKUP(E23,index.html!E:E,index.html!F:F)," ") -> 签证与搬迁支持
A24: 314 | B24: Header Nav | C24: Apply Now | D24: =IFERROR(_xlfn.XLOOKUP(C24,index.html!C:C,index.html!D:D)," ") -> 立即申请 | E24: 立即申请
A25: 333 | B25: Hero | C25: 全球最大BPO企业，为华语人才提供Career机会 | D25: 全球最大BPO企业，为中文人才提供职涯机会 | E25: 全球最大业务流程外包企业，为华语人才提供职业机会 | F25: 全球最大业务流程外包企业，为中文人才提供职业机会
A26: 342 | B26: About Text | C26: TP是全球领先的BPO（Business Process Outsourcing）企业 | E26: TP是全球领先的业务流程外包企业
A27: 345 | B27: About Text | C27: 为全球知名Brand提供卓越的Customer Experience服务 | D27: =IFERROR(_xlfn.XLOOKUP(C27,index.html!C:C,index.html!D:D)," ") -> 为国际知名品牌提供客户体验服务 | E27: 为全球知名品牌提供卓越的客户体验服务
A28: 348 | B28: About Text | C28: 无论你是Fresh Graduate还是经验丰富的Professional | D28: =IFERROR(_xlfn.XLOOKUP(C28,index.html!C:C,index.html!D:D)," ") -> 无论你是Fresh Graduate还是有工作经验 | E28: 无论你是应届毕业生还是经验丰富的专业人士
A29: 361 | B29: GPTW | C29: TP 荣获 Great Place to Work® 评选的「World's Best Workplaces™」 | E29: TP 荣获卓越职场研究机构评选的「全球最佳职场」
A30: 376 | B30: GPTW Stats | C30: 全球 Employee 人数 | D30: =IFERROR(_xlfn.XLOOKUP(C30,index.html!C:C,index.html!D:D)," ") -> 全球员工人数 | E30: 全球员工人数
A31: 391 | B31: Stats | C31: MY/TH员工 | D31: =IFERROR(_xlfn.XLOOKUP(C31,index.html!C:C,index.html!D:D)," ") -> 马来西亚/泰国员工 | E31: 马来西亚/泰国员工
A32: 430 | B32: Footer | C32: Open Jobs | D32: =IFERROR(_xlfn.XLOOKUP(C32,index.html!C:C,index.html!D:D)," ") -> 在招职位 | E32: 职位列表
A33: 449 | B33: Floating | C33: Apply Now | D33: =IFERROR(_xlfn.XLOOKUP(C33,index.html!C:C,index.html!D:D)," ") -> 立即申请 | E33: 立即申请
A34: 449 | B34: Floating | C34: 轻松面谈 | D34: 初步沟通 | E34: 轻松面谈

Sheet area-around-office
A1: Field | B1: Value
A2: Page URL | B2: https://tpmyandtpth.github.io/MLP/area-around-office.html
A3: Page Title (EN) | B3: Area Around Office
A4: Page Title (CN) | B4: 周边环境 | TP招聘 马来西亚·泰国
A5: Created Date | B5: 2026-01-27
A6: Translator | B6: Claude AI
A7: Review Date | B7: 46064
A8: Reviewer Name | B8: Anna Saw
A9: Review Status | B9: Completed
A10: Version | B10: v1.0
A13: Content Review Table
A15: Line # | B15: Section | C15: Local Mandarin (Mixed English) | D15: Local Comment | E15: Native Mandarin | F15: Native Comment
A16: 287 | B16: Lang Toggle | C16: 🇲🇾 本地华人 | E16: 🇲🇾 本地华人
A17: 288 | B17: Lang Toggle | C17: 🌏 海外华人 | E17: 🌏 海外华人
A18: 333 | B18: Hero | C18: 便捷的交通，丰富的美食，舒适的生活。这些是我们每天最看重的事。 | D18: =IFERROR(_xlfn.XLOOKUP(C18,index.html!C:C,index.html!D:D)," ") | E18: 便捷交通、丰富美食、舒适生活。好的日常环境，让我们专注于工作和成长。 | F18: =IFERROR(_xlfn.XLOOKUP(E18,index.html!E:E,index.html!F:F)," ")
A19: 340 | B19: Pill Nav | C19: 员工分享 | D19: =IFERROR(_xlfn.XLOOKUP(C19,index.html!C:C,index.html!D:D)," ") | E19: 员工分享 | F19: =IFERROR(_xlfn.XLOOKUP(E19,index.html!E:E,index.html!F:F)," ")
A20: 348 | B20: KL Lead | C20: 城市繁华与绿色兼备，多元文化在这里共融。交通便利、美食众多、娱乐活动丰富。 | D20: 城市繁华又有绿色空间，多元文化融合在这里。交通方便、美食多、娱乐丰富。 | E20: 城市繁华与自然风景结合，多民族文化在此汇聚。便捷的交通、多样的美食、丰富的娱乐选择。 | F20: =IFERROR(_xlfn.XLOOKUP(E20,index.html!E:E,index.html!F:F)," ")
A21: 364 | B21: KL Card | C21: 交通出行 | D21: =IFERROR(_xlfn.XLOOKUP(C21,index.html!C:C,index.html!D:D)," ") | E21: 交通出行 | F21: =IFERROR(_xlfn.XLOOKUP(E21,index.html!E:E,index.html!F:F)," ")
A22: 365 | B22: KL Card | C22: 轻轨、公交、打车应用齐全，上班通勤便捷。位于市中心，出行方便。 | D22: 交通方便，有LRT、巴士，也可以用Grab。上班出行很轻松，市中心位置也很方便。 | E22: 地铁、公交、打车应用一应俱全。中心位置，通勤快速便捷。 | F22: =IFERROR(_xlfn.XLOOKUP(E22,index.html!E:E,index.html!F:F)," ")
A23: 369 | B23: KL Card | C23: 美食选择 | D23: =IFERROR(_xlfn.XLOOKUP(C23,index.html!C:C,index.html!D:D)," ") | E23: 美食选择 | F23: =IFERROR(_xlfn.XLOOKUP(E23,index.html!E:E,index.html!F:F)," ")
A24: 370 | B24: KL Card | C24: 街边小摊、本地菜、日本料理、咖啡厅应有尽有。吃饭便宜，总能发现新的美食。 | D24: =IFERROR(_xlfn.XLOOKUP(C24,index.html!C:C,index.html!D:D)," ") | E24: 小食摊、本地菜、日本料理、特色咖啡应有尽有。外食便宜，每天都有新发现。 | F24: =IFERROR(_xlfn.XLOOKUP(E24,index.html!E:E,index.html!F:F)," ")
A25: 374 | B25: KL Card | C25: 运动休闲 | D25: =IFERROR(_xlfn.XLOOKUP(C25,index.html!C:C,index.html!D:D)," ") | E25: 运动休闲 | F25: =IFERROR(_xlfn.XLOOKUP(E25,index.html!E:E,index.html!F:F)," ")
A26: 375 | B26: KL Card | C26: 公寓有健身房和游泳池，市内公园和运动设施齐全。工作之余，轻松放松身心。 | D26: =IFERROR(_xlfn.XLOOKUP(C26,index.html!C:C,index.html!D:D)," ") | E26: 公寓配备健身房、游泳池，周边运动设施完善。工作之余，轻松运动放松。 | F26: =IFERROR(_xlfn.XLOOKUP(E26,index.html!E:E,index.html!F:F)," ")
A27: 385 | B27: Penang Lead | C27: 靠海的小岛，有着慢生活的节奏。环境宁静，生活成本低，风景优美。 | D27: =IFERROR(_xlfn.XLOOKUP(C27,index.html!C:C,index.html!D:D)," ") | E27: 滨海小岛，悠闲舒适的生活节奏。环境宁静、成本低廉、自然风景优美。 | F27: =IFERROR(_xlfn.XLOOKUP(E27,index.html!E:E,index.html!F:F)," ")
A28: 404 | B28: Penang Card | C28: 打车应用是出门首选。无论住在海边还是市区，通勤都很轻松。 | D28: 用Grab最方便，不管住海边还是市区，通勤都很轻松。 | E28: 打车应用方便快捷。海边或市区都很容易出行。 | F28: =IFERROR(_xlfn.XLOOKUP(E28,index.html!E:E,index.html!F:F)," ")
A29: 409 | B29: Penang Card | C29: 街边小摊、美食广场、咖啡馆文化浓厚。各地美食应有尽有，天天吃不一样。 | D29: 街边小摊、美食广场、咖啡馆文化浓厚。各地美食应有尽有，天天都可以吃不一样。 | E29: 小摊美食、广场小食、咖啡文化浓厚。多元美食选择，每天不重样。 | F29: =IFERROR(_xlfn.XLOOKUP(E29,index.html!E:E,index.html!F:F)," ")
A30: 414 | B30: Penang Card | C30: 海滨散步、海滩游玩、咖啡厅小坐。慢生活在这里很常见。 | D30: 海边散步、去海滩玩、或者坐在咖啡厅喝咖啡，这里的生活节奏很悠闲。 | E30: 海边漫步、沙滩游玩、咖啡聚会。悠闲的生活方式在这里很普遍。 | F30: =IFERROR(_xlfn.XLOOKUP(E30,index.html!E:E,index.html!F:F)," ")
A31: 424 | B31: Bangkok Lead | C31: 东南亚最国际化的城市，发达的交通、完善的服务、丰富的选择。 | D31: 东南亚超国际化的城市，交通便利、服务好、选择多。 | E31: 东南亚最国际化城市，发达交通、完善服务、丰富选择。 | F31: =IFERROR(_xlfn.XLOOKUP(E31,index.html!E:E,index.html!F:F)," ")
A32: 443 | B32: Bangkok Card | C32: 地铁网络发达，主要区域都能直达。打车应用也很方便实惠。 | D32: 地铁去主要地方都很方便，用Grab打车也省事又划算。 | E32: 地铁网络发达，覆盖主要区域。打车应用便宜便捷。 | F32: =IFERROR(_xlfn.XLOOKUP(E32,index.html!E:E,index.html!F:F)," ")
A33: 447 | B33: Bangkok Card | C33: 日式便利 | D33: 华语便利 | E33: 日式便利 | F33: 华语便利
A34: 448 | B34: Bangkok Card | C34: 日本餐厅、日用品、医疗服务，日语支持完善。新手也能快速适应。 | D34: 华人餐厅、中式日用品、医疗服务，中文支持完善。新手也能很快适应生活。 | E34: 日本餐厅、日用品、医疗服务齐全。日语支持完善，新手也能快速上手。 | F34: 华人餐厅、中式日用品、医疗服务，中文支持完善。新手也能很快适应生活。
A35: 453 | B35: Bangkok Card | C35: 大型商场、特色餐厅、各类活动。工作之余，生活很丰富多彩。 | D35: =IFERROR(_xlfn.XLOOKUP(C35,index.html!C:C,index.html!D:D)," ") | E35: 大型商城、特色美食、活动众多。工作之余，有很多方式放松。 | F35: =IFERROR(_xlfn.XLOOKUP(E35,index.html!E:E,index.html!F:F)," ")
A36: 462 | B36: Tips Quote | C36: "随便找个街边小摊吃饭，既便宜又好吃。现在我特别喜欢在这里生活。" | D36: =IFERROR(_xlfn.XLOOKUP(C36,index.html!C:C,index.html!D:D)," ") | E36: "吃饭选择太多了，街边、商场、日本菜样样有。成本低，吃得又开心。" | F36: =IFERROR(_xlfn.XLOOKUP(E36,index.html!E:E,index.html!F:F)," ")
A37: 470 | B37: Tips Quote | C37: "大海就在身边，周末约朋友去海边咖啡厅，非常放松。" | D37: =IFERROR(_xlfn.XLOOKUP(C37,index.html!C:C,index.html!D:D)," ") | E37: "靠近大海特别好，周末海边散步、咖啡厅小坐，工作压力都减半了。" | F37: =IFERROR(_xlfn.XLOOKUP(E37,index.html!E:E,index.html!F:F)," ")
A38: 478 | B38: Tips Quote | C38: "地铁真的很方便，下班后可以直接去商场或咖啡厅。生活便利度很高。" | D38: =IFERROR(_xlfn.XLOOKUP(C38,index.html!C:C,index.html!D:D)," ") | E38: "地铁四通八达，下班后想去哪就去哪。这座城市节奏快但很有活力。" | F38: =IFERROR(_xlfn.XLOOKUP(E38,index.html!E:E,index.html!F:F)," ")
A39: 499 | B39: Disclaimer | C39: 部分图片为示意图。实际工作地点、通勤方式、办公设施会因项目和时期有所不同。 | D39: =IFERROR(_xlfn.XLOOKUP(C39,index.html!C:C,index.html!D:D)," ") | E39: 部分图片为示意。具体工作地点、通勤路线、办公环境因项目而异。 | F39: =IFERROR(_xlfn.XLOOKUP(E39,index.html!E:E,index.html!F:F)," ")
A40: 506 | B40: CTA Card | C40: 华语职位众多，欢迎没有经验的朋友。 | D40: =IFERROR(_xlfn.XLOOKUP(C40,index.html!C:C,index.html!D:D)," ") | E40: 华语岗位丰富，欢迎应届毕业生和职场新手。 | F40: =IFERROR(_xlfn.XLOOKUP(E40,index.html!E:E,index.html!F:F)," ")
A41: 511 | B41: CTA Card | C41: 不是正式面试，只是聊天了解一下。用日语提问也没问题。 | D41: 不是正式面试，只是聊天了解一下。用中文提问也没问题。 | E41: 非正式面试，就是友好的聊天。用日语提问也完全可以。 | F41: 不是正式面试，只是聊天了解一下。用中文提问也没问题。
A42: 516 | B42: CTA Card | C42: 最新职位、生活资讯、工作建议。有问题也可以直接问。 | D42: =IFERROR(_xlfn.XLOOKUP(C42,index.html!C:C,index.html!D:D)," ") | E42: 最新职位、当地资讯、工作提示。有任何问题都能直接提。 | F42: =IFERROR(_xlfn.XLOOKUP(E42,index.html!E:E,index.html!F:F)," ")

Sheet casual-interview
A1: Field | B1: Value
A2: Page URL | B2: https://tpmyandtpth.github.io/MLP/casual-interview.html
A3: Page Title (EN) | B3: Casual Interview
A4: Page Title (CN) | B4: 休闲面谈 | TP招聘 马来西亚·泰国
A5: Created Date | B5: 2026-01-27
A6: Translator | B6: Claude AI
A7: Review Date | B7: 46064
A8: Reviewer Name | B8: Anna Saw
A9: Review Status | B9: Completed
A10: Version | B10: v1.0
A13: Content Review Table
A15: Line # | B15: Section | C15: Local Mandarin (Mixed English) | D15: Local Comment | E15: Native Mandarin | F15: Native Comment
A16: 287 | B16: Lang Toggle | C16: 🇲🇾 本地华人 | E16: 🇲🇾 本地华人
A17: 288 | B17: Lang Toggle | C17: 🌏 海外华人 | E17: 🌏 海外华人
A18: 310 | B18: Header Nav | C18: Home | D18: =IFERROR(_xlfn.XLOOKUP(C18,index.html!C:C,index.html!D:D)," ") | E18: 首页
A19: 311 | B19: Header Nav | C19: About TP | D19: =IFERROR(_xlfn.XLOOKUP(C19,index.html!C:C,index.html!D:D)," ") | E19: 关于TP
A20: 312 | B20: Header Nav | C20: Benefits | D20: 薪资福利 | E20: 薪资福利
A21: 313 | B21: Header Nav | C21: Hiring Process | D21: 招聘流程 | E21: 招聘流程
A22: 316 | B22: Header Nav | C22: Visa Support | D22: =IFERROR(_xlfn.XLOOKUP(C22,index.html!C:C,index.html!D:D)," ") | E22: 签证支持
A23: 317 | B23: Header Nav | C23: Apply Now | D23: =IFERROR(_xlfn.XLOOKUP(C23,index.html!C:C,index.html!D:D)," ") -> 立即申请 | E23: 立即申请
A24: 336 | B24: Brand Tagline | C24: Malaysia·Thailand | D24: =IFERROR(_xlfn.XLOOKUP(C24,index.html!C:C,index.html!D:D)," ") | E24: 马来西亚·泰国 | F24: =IFERROR(_xlfn.XLOOKUP(E24,index.html!E:E,index.html!F:F)," ")
A25: 355 | B25: Hero H1 | C25: Casual Chat进行中！— 先easy，用华语consult吧 | D25: 随意聊天进行中！— 先轻松聊，用华语咨询吧 | E25: 休闲面谈进行中！— 先轻松，用华语咨询吧 | F25: =IFERROR(_xlfn.XLOOKUP(E25,index.html!E:E,index.html!F:F)," ")
A26: 359 | B26: Hero P | C26: 关于Malaysia·Thailand的「work」「work style」「life cost」「住所」，30分钟online（Microsoft Teams）guide你。不是interview。No experience的朋友，考虑转职的朋友也welcome。 | D26: 关于马来西亚和泰国的「工作」「工作方式」「生活成本」「住宿」，30分钟线上（Microsoft Teams）带你了解。不是面试哦。没有经验的朋友、考虑转职的朋友也欢迎加入。 | E26: 关于马来西亚·泰国的「工作」「工作方式」「生活费」「住所」，30分钟线上（Microsoft Teams）指引你。不是面试。无经验的朋友，考虑转职的朋友也欢迎。 | F26: =IFERROR(_xlfn.XLOOKUP(E26,index.html!E:E,index.html!F:F)," ")
A27: 365 | B27: Hero CTA | C27: Open面谈Form → | D27: 开放面试表格 | E27: 打开面谈表单 → | F27: =IFERROR(_xlfn.XLOOKUP(E27,index.html!E:E,index.html!F:F)," ")
A28: 366 | B28: Hero CTA | C28: 看面谈Content | D28: 查看面试内容 | E28: 看面谈内容 | F28: =IFERROR(_xlfn.XLOOKUP(E28,index.html!E:E,index.html!F:F)," ")
A29: 375 | B29: Section Title | C29: Casual Chat的Point | D29: 随意聊天的重点 | E29: 休闲面谈的要点 | F29: =IFERROR(_xlfn.XLOOKUP(E29,index.html!E:E,index.html!F:F)," ")
A30: 378 | B30: Section Subtitle | C30: 短时间solve不安和疑问。Apply前，先information收集。 | D30: 短时间解决你的疑问和不安。在申请前，先收集信息。 | E30: 短时间解决不安和疑问。申请前，先信息收集。 | F30: =IFERROR(_xlfn.XLOOKUP(E30,index.html!E:E,index.html!F:F)," ")
A31: 382 | B31: Point Card | C31: 不是Interview | D31: 不是面试 | E31: 不是面试 | F31: =IFERROR(_xlfn.XLOOKUP(E31,index.html!E:E,index.html!F:F)," ")
A32: 383 | B32: Point Card | C32: No pass/fail。Information提供和consult目的的casual场。 | D32: 没有通过或不通过的考核。这里是提供信息和咨询的轻松场合。 | E32: 没有通过/不通过。信息提供和咨询目的的休闲场合。 | F32: =IFERROR(_xlfn.XLOOKUP(E32,index.html!E:E,index.html!F:F)," ")
A33: 387 | B33: Point Card | C33: Online 30分钟 | D33: =IFERROR(_xlfn.XLOOKUP(C33,index.html!C:C,index.html!D:D)," ") | E33: 线上30分钟 | F33: =IFERROR(_xlfn.XLOOKUP(E33,index.html!E:E,index.html!F:F)," ")
A34: 388 | B34: Point Card | C34: Microsoft Teams实施。Phone／PC都OK。 | D34: 通过Microsoft Teams进行。手机或电脑都可以。 | E34: Microsoft Teams实施。手机／电脑都OK。 | F34: =IFERROR(_xlfn.XLOOKUP(E34,index.html!E:E,index.html!F:F)," ")
A35: 392 | B35: Point Card | C35: 华语Support | D35: =IFERROR(_xlfn.XLOOKUP(C35,index.html!C:C,index.html!D:D)," ") | E35: 华语支持
A36: 393 | B36: Point Card | C36: 华语speaker的staff对应。English不confident也没problem。 | D36: 有华语招聘者对应，即使英文不太自信也没问题。 | E36: 华语使用者的员工对应。英语不自信也没问题。 | F36: =IFERROR(_xlfn.XLOOKUP(E36,index.html!E:E,index.html!F:F)," ")
A37: 397 | B37: Point Card | C37: No Experience·迷い Welcome | D37: 没有经验或还在犹豫的朋友都欢迎。 | E37: 无经验·犹豫 欢迎 | F37: 没有经验或还在犹豫的朋友都欢迎。
A38: 398 | B38: Point Card | C38: Work experience有无不问。还没decide转职也OK。 | D38: 有无工作经验都可以，没决定是否转职也没关系。 | E38: 工作经验有无不问。还没决定转职也OK。 | F38: 有无工作经验都可以，没决定是否转职也没关系。
A39: 403 | B39: CTA Button | C39: Book 30分钟面谈 | D39: 预约30分钟面谈 | E39: 预约30分钟面谈 | F39: =IFERROR(_xlfn.XLOOKUP(E39,index.html!E:E,index.html!F:F)," ")
A40: 404 | B40: CTA Note | C40: ※ Form submit后，staff会contact你日程adjust。 | D40: ※ 提交表格后，招聘者会联系你调整时间。 | E40: ※ 表单提交后，员工会联系你日程调整。 | F40: =IFERROR(_xlfn.XLOOKUP(E40,index.html!E:E,index.html!F:F)," ")
A41: 411 | B41: Section Title | C41: 实施Method和当日Flow | D41: 实施方式和当天流程 | E41: 实施方法和当日流程 | F41: =IFERROR(_xlfn.XLOOKUP(E41,index.html!E:E,index.html!F:F)," ")
A42: 414 | B42: Section Subtitle | C42: Online完结。Smooth参加。 | D42: 全程线上完成，参与轻松顺畅。 | E42: 线上完结。顺畅参加。 | F42: 全程线上完成，参与轻松顺畅。
A43: 419 | B43: Step | C43: 从Form Apply | D43: 从表格申请开始 | E43: 从表单申请 | F43: 从表格申请开始
A44: 420 | B44: Step | C44: Simple项目input然后submit。 | D44: 填写简单资料然后提交 | E44: 简单项目输入然后提交。 | F44: =IFERROR(_xlfn.XLOOKUP(E44,index.html!E:E,index.html!F:F)," ")
A45: 424 | B45: Step | C45: Receive Teams Link | D45: 收到 Teams 链接 | E45: 收到Teams链接 | F45: =IFERROR(_xlfn.XLOOKUP(E45,index.html!E:E,index.html!F:F)," ")
A46: 425 | B46: Step | C46: Staff会日程adjust和meeting URL guide。 | D46: 招聘者会帮你安排时间并提供会议链接 | E46: 员工会日程调整和会议URL指引。 | F46: =IFERROR(_xlfn.XLOOKUP(E46,index.html!E:E,index.html!F:F)," ")
A47: 429 | B47: Step | C47: 华语30分钟Consult | D47: 华语30分钟咨询 | E47: 华语30分钟咨询 | F47: =IFERROR(_xlfn.XLOOKUP(E47,index.html!E:E,index.html!F:F)," ")
A48: 430 | B48: Step | C48: Depend on你的situation，work·life的疑问answer。 | D48: 根据你的情况，解答工作和生活相关疑问 | E48: 根据你的情况，工作·生活的疑问回答。 | F48: =IFERROR(_xlfn.XLOOKUP(E48,index.html!E:E,index.html!F:F)," ")
A49: 437 | B49: Agenda | C49: Sample Agenda（30分钟） | D49: 30分钟参考流程 | E49: 样本议程（30分钟） | F49: 30分钟参考流程
A50: 439 | B50: Agenda Item | C50: 自我介绍（你的希望·experience share） | D50: 自我介绍（分享你的期望和经验） | E50: 自我介绍（你的希望·经验分享） | F50: 自我介绍（分享你的期望和经验）
A51: 440 | B51: Agenda Item | C51: Work／work style的explain | D51: 讲解工作内容和工作方式 | E51: 工作／工作方式的说明 | F51: =IFERROR(_xlfn.XLOOKUP(E51,index.html!E:E,index.html!F:F)," ")
A52: 441 | B52: Agenda Item | C52: Life cost·住所的basic info | D52: 生活成本和住宿基本信息 | E52: 生活费·住所的基本信息 | F52: =IFERROR(_xlfn.XLOOKUP(E52,index.html!E:E,index.html!F:F)," ")
A53: 442 | B53: Agenda Item | C53: Selection process的flow（希望的人only） | D53: 招聘流程说明（仅限有兴趣的人 | E53: 选拔流程的说明（希望的人才有） | F53: 选拔流程的说明（仅限有兴趣的人）
A54: 443 | B54: Agenda Item | C54: Q&A／next step guide | D54: 问答环节及下一步指导 | E54: 问答／下一步指引 | F54: =IFERROR(_xlfn.XLOOKUP(E54,index.html!E:E,index.html!F:F)," ")
A55: 447 | B55: Topics | C55: 可以Consult的Topic | D55: 可咨询的主题 | E55: 可以咨询的话题 | F55: =IFERROR(_xlfn.XLOOKUP(E55,index.html!E:E,index.html!F:F)," ")
A56: 449 | B56: Topics Item | C56: Work：华语position的type等 | D56: 工作：华语职位类型等 | E56: 工作：华语职位的类型等 | F56: =IFERROR(_xlfn.XLOOKUP(E56,index.html!E:E,index.html!F:F)," ")
A57: 450 | B57: Topics Item | C57: Work style：Shift／work type等 | D57: 工作方式：轮班/工作类型等 | E57: 工作方式：轮班／工作形态等 | F57: =IFERROR(_xlfn.XLOOKUP(E57,index.html!E:E,index.html!F:F)," ")
A58: 451 | B58: Topics Item | C58: Life cost：Food·transport·rent的目安 | D58: 生活成本：饮食、交通、租金参考 | E58: 生活费：餐饮·交通·租金的参考 | F58: =IFERROR(_xlfn.XLOOKUP(E58,index.html!E:E,index.html!F:F)," ")
A59: 452 | B59: Topics Item | C59: 住所：Property type和找房basic | D59: 住宿：房型及找房基础信息 | E59: 住所：房产类型和找房基本 | F59: =IFERROR(_xlfn.XLOOKUP(E59,index.html!E:E,index.html!F:F)," ")
A60: 458 | B60: CTA Button | C60: Now Book（Free） | D60: 立即预约（免费） | E60: 立即预约（免费） | F60: =IFERROR(_xlfn.XLOOKUP(E60,index.html!E:E,index.html!F:F)," ")
A61: 465 | B61: Section Title | C61: 负责Team（华语对应） | D61: 负责团队（华语支持） | E61: 负责团队（华语对应） | F61: =IFERROR(_xlfn.XLOOKUP(E61,index.html!E:E,index.html!F:F)," ")
A62: 468 | B62: Section Subtitle | C62: 从apply到入职，华语伴走。 | D62: 从申请到入职，全程有华语陪伴 | E62: 从申请到入职，华语陪伴。 | F62: =IFERROR(_xlfn.XLOOKUP(E62,index.html!E:E,index.html!F:F)," ")
A63: 476 | B63: Team Member | C63: 招聘Staff | D63: 招聘工作人员 | E63: 招聘员工 | F63: =IFERROR(_xlfn.XLOOKUP(E63,index.html!E:E,index.html!F:F)," ")
A64: 484 | B64: CTA Button | C64: Submit面谈Form → | D64: 提交面谈表格 → | E64: 提交面谈表单 → | F64: =IFERROR(_xlfn.XLOOKUP(E64,index.html!E:E,index.html!F:F)," ")
A65: 491 | B65: FAQ Title | C65: FAQ（Casual Chat） | D65: FAQ （随意聊天） | E65: 常见问题（休闲面谈） | F65: =IFERROR(_xlfn.XLOOKUP(E65,index.html!E:E,index.html!F:F)," ")
A66: 496 | B66: FAQ Q | C66: Q. 面谈是interview吗？ | D66: =IFERROR(_xlfn.XLOOKUP(C66,index.html!C:C,index.html!D:D)," ") | E66: Q. 面谈是面试吗？ | F66: =IFERROR(_xlfn.XLOOKUP(E66,index.html!E:E,index.html!F:F)," ")
A67: 497 | B67: FAQ A | C67: 不是。不进行pass/fail判断。Information提供和consult的场。 | D67: 不是。不进行pass/fail判断。只是提供信息和咨询的轻松场合。。 | E67: 不是。不进行通过/不通过判断。信息提供和咨询的场合。 | F67: =IFERROR(_xlfn.XLOOKUP(E67,index.html!E:E,index.html!F:F)," ")
A68: 500 | B68: FAQ Q | C68: Q. 所需时间approximately多久？ | D68: Q：大概需要多久？ | E68: Q. 所需时间大约多久？ | F68: =IFERROR(_xlfn.XLOOKUP(E68,index.html!E:E,index.html!F:F)," ")
A69: 501 | B69: FAQ A | C69: 目安是30分钟（Microsoft Teams）。 | D69: 大约30分钟（Microsoft Teams） | E69: 参考是30分钟（Microsoft Teams）。 | F69: =IFERROR(_xlfn.XLOOKUP(E69,index.html!E:E,index.html!F:F)," ")
A70: 504 | B70: FAQ Q | C70: Q. English不confident也OK？ | D70: Q:英文不自信也可以吗？ | E70: Q. 英语不自信也OK？ | F70: =IFERROR(_xlfn.XLOOKUP(E70,index.html!E:E,index.html!F:F)," ")
A71: 505 | B71: FAQ A | C71: 华语guide。English不confident也no problem。 | D71: 有华语进行沟通，英文不自信也没问题 | E71: 华语指引。英语不自信也没问题。 | F71: =IFERROR(_xlfn.XLOOKUP(E71,index.html!E:E,index.html!F:F)," ")
A72: 508 | B72: FAQ Q | C72: Q. 还没decide转职。 | D72: Q:还没决定转职怎么办？ | E72: Q. 还没决定转职。 | F72: =IFERROR(_xlfn.XLOOKUP(E72,index.html!E:E,index.html!F:F)," ")
A73: 509 | B73: FAQ A | C73: No problem。Information收集和考虑阶段也easy参加。 | D73: 没问题。收集信息和考虑阶段也可以轻松参与 | E73: 没问题。信息收集和考虑阶段也轻松参加。 | F73: =IFERROR(_xlfn.XLOOKUP(E73,index.html!E:E,index.html!F:F)," ")
A74: 514 | B74: CTA Button | C74: Book Now | D74: 立即预约 | E74: 立即预约 | F74: =IFERROR(_xlfn.XLOOKUP(E74,index.html!E:E,index.html!F:F)," ")
A75: 516 | B75: CTA Note | C75: 最新info是 LINE Official Account 也发信中。 | D75: 最新信息也会通过 LINE 官方账号发送 | E75: 最新信息在 LINE官方账号 也发布中。 | F75: =IFERROR(_xlfn.XLOOKUP(E75,index.html!E:E,index.html!F:F)," ")
A76: 540 | B76: Floating | C76: Apply Now | D76: =IFERROR(_xlfn.XLOOKUP(C76,index.html!C:C,index.html!D:D)," ") -> 立即申请 | E76: 立即申请
A77: 542 | B77: Floating | C77: Casual Chat | D77: 初步沟通 | E77: 休闲面谈 | F77: =IFERROR(_xlfn.XLOOKUP(E77,index.html!E:E,index.html!F:F)," ")

Sheet cost-of-living
A1: Field | B1: Value
A2: Page URL | B2: https://tpmyandtpth.github.io/MLP/cost-of-living.html
A3: Page Title (EN) | B3: Cost of Living
A4: Page Title (CN) | B4: 生活成本 | TP招聘 马来西亚·泰国
A5: Created Date | B5: 2026-01-27
A6: Translator | B6: Claude AI
A7: Review Date | B7: 46065
A8: Reviewer Name | B8: Anna Saw
A9: Review Status | B9: Completed
A10: Version | B10: v1.0
A13: Content Review Table
A15: Line # | B15: Section | C15: Local Mandarin (Mixed English) | D15: Local Comment | E15: Native Mandarin | F15: Native Comment
A16: 287 | B16: Lang Toggle | C16: 🇲🇾 本地华人 | E16: 🇲🇾 本地华人
A17: 288 | B17: Lang Toggle | C17: 🌏 海外华人 | E17: 🌏 海外华人
A18: 333 | B18: Hero H1 | C18: 生活成本 | D18: =IFERROR(_xlfn.XLOOKUP(C18,index.html!C:C,index.html!D:D)," ") | E18: 生活成本
A19: 334 | B19: Hero P | C19: 同样的工资，在马来西亚可以过得更舒适、更自由。用更少的钱，享受更好的生活品质。 | D19: =IFERROR(_xlfn.XLOOKUP(C19,index.html!C:C,index.html!D:D)," ") | E19: 同样的收入，在马来西亚生活会更宽裕。低成本、高质量、更自由的生活方式。
A20: 337 | B20: Hero CTA | C20: 查看职位 | D20: =IFERROR(_xlfn.XLOOKUP(C20,index.html!C:C,index.html!D:D)," ") | E20: 查看职位
A21: 338 | B21: Hero CTA | C21: 移居支持 | D21: =IFERROR(_xlfn.XLOOKUP(C21,index.html!C:C,index.html!D:D)," ") | E21: 移居支持 | F21: 移居协助
A22: 356 | B22: Section Title | C22: 快速对比（费用/中国/马来西亚） | D22: =IFERROR(_xlfn.XLOOKUP(C22,index.html!C:C,index.html!D:D)," ") | E22: 快速对比（项目/中国/马来西亚）
A23: 361 | B23: Table Header | C23: 中国（北京） | D23: =IFERROR(_xlfn.XLOOKUP(C23,index.html!C:C,index.html!D:D)," ") | E23: 中国大陆
A24: 362 | B24: Table Row | C24: 家租（1卧） | D24: =IFERROR(_xlfn.XLOOKUP(C24,index.html!C:C,index.html!D:D)," ") | E24: 家租（1卧室） | F24: 一居室月租
A25: 362 | B25: Table Row | C25: ￥8000-12000+ | D25: =IFERROR(_xlfn.XLOOKUP(C25,index.html!C:C,index.html!D:D)," ") | E25: ¥8000-12000+
A26: 362 | B26: Table Row | C26: RM1700-2500（配24h保安、游泳池、健身房） | D26: =IFERROR(_xlfn.XLOOKUP(C26,index.html!C:C,index.html!D:D)," ") | E26: RM1700-2500（约5400-8000元），含24h保安、游泳池、健身房
A27: 363 | B27: Table Row | C27: 餐饮（一餐） | D27: =IFERROR(_xlfn.XLOOKUP(C27,index.html!C:C,index.html!D:D)," ") | E27: 就餐（一餐）
A28: 363 | B28: Table Row | C28: RM10-15 | D28: =IFERROR(_xlfn.XLOOKUP(C28,index.html!C:C,index.html!D:D)," ") | E28: RM10-15（约30-50元）
A29: 364 | B29: Table Row | C29: 交通（月） | D29: =IFERROR(_xlfn.XLOOKUP(C29,index.html!C:C,index.html!D:D)," ") | E29: 交通费（月）
A30: 364 | B30: Table Row | C30: RM150-300（含轻轨和打车） | D30: =IFERROR(_xlfn.XLOOKUP(C30,index.html!C:C,index.html!D:D)," ") | E30: RM150-300（约480-960元），地铁+打车
A31: 369 | B31: Table Note | C31: 物价便宜，同工资可以过得更舒适。 | D31: =IFERROR(_xlfn.XLOOKUP(C31,index.html!C:C,index.html!D:D)," ") | E31: 汇率参考：1RM≈3.2元。具体费用根据生活方式变化。
A32: 374 | B32: Section Title | C32: 月度预算范例 | D32: =IFERROR(_xlfn.XLOOKUP(C32,index.html!C:C,index.html!D:D)," ") | E32: 月度预算范例
A33: 378 | B33: Budget Card | C33: 单身，吉隆坡（1卧） | D33: =IFERROR(_xlfn.XLOOKUP(C33,index.html!C:C,index.html!D:D)," ") | E33: 单身住户，吉隆坡
A34: 395 | B34: Budget Card | C34: 单身，槟城（1卧） | D34: =IFERROR(_xlfn.XLOOKUP(C34,index.html!C:C,index.html!D:D)," ") | E34: 单身住户，槟城
A35: 412 | B35: Budget Card | C35: 情侣，吉隆坡（2卧） | D35: =IFERROR(_xlfn.XLOOKUP(C35,index.html!C:C,index.html!D:D)," ") | E35: 两人共居，吉隆坡
A36: 430 | B36: Budget Note | C36: 以上仅为参考。具体费用因生活方式和汇率而异。 | D36: =IFERROR(_xlfn.XLOOKUP(C36,index.html!C:C,index.html!D:D)," ") | E36: 以上数字仅供参考，具体费用因人而异。
... A41: 477 | B41: Voice | C41: "周末打打车去郊外，成本只是北京的零头。自由度真的不一样。" | D41: =IFERROR(_xlfn.XLOOKUP(C41,index.html!C:C,index.html!D:D)," ") | E41: "周末打车兜风，成本只是国内的几分之一。自由度完全不同。"
A42: 485 | B42: Tips Title | C42: 节省生活成本的秘诀 | D42: =IFERROR(_xlfn.XLOOKUP(C42,index.html!C:C,index.html!D:D)," ") | E42: 降低生活成本的方法 | F42: 节省生活成本的秘诀
A43: 489 | B43: Tips Card | C43: 选择靠近工作地的住房 | D43: =IFERROR(_xlfn.XLOOKUP(C43,index.html!C:C,index.html!D:D)," ") | E43: 住处靠近工作地 | F43: 居住地点临近工作地点
A44: 490 | B44: Tips Card | C44: 轻轨沿线的公寓降低交通成本。Grab费用也会减少。 | D44: =IFERROR(_xlfn.XLOOKUP(C44,index.html!C:C,index.html!D:D)," ") | E44: 地铁沿线的公寓减少交通支出。打车费用也会大幅下降。
A45: 494 | B45: Tips Card | C45: 善用本地美食和食阁 | D45: =IFERROR(_xlfn.XLOOKUP(C45,index.html!C:C,index.html!D:D)," ") | E45: 尝试本地美食和食堂
A46: 495 | B46: Tips Card | C46: 街边小摊和美食广场的食物便宜又好吃。既省钱又有本地体验。 | D46: =IFERROR(_xlfn.XLOOKUP(C46,index.html!C:C,index.html!D:D)," ") | E46: 小食摊和美食广场价格实惠又地道。既省钱又能尝试当地风味。
A47: 499 | B47: Tips Card | C47: 合理选择通讯套餐 | D47: =IFERROR(_xlfn.XLOOKUP(C47,index.html!C:C,index.html!D:D)," ") | E47: 选择合适的通讯套餐 | F47: 选择合适的通信套餐
A48: 500 | B48: Tips Card | C48: 预付套餐和低价方案很常见。根据实际使用来选择。 | D48: =IFERROR(_xlfn.XLOOKUP(C48,index.html!C:C,index.html!D:D)," ") | E48: 预付卡和低价套餐选择多。根据自己需求灵活选择。 | F48: 预付卡和优惠套餐种类多样，可灵活搭配
A49: 507 | B49: CTA Card | C49: 华语职位众多，欢迎应届生和职场新人申请。 | D49: =IFERROR(_xlfn.XLOOKUP(C49,index.html!C:C,index.html!D:D)," ") | E49: 华语岗位丰富，欢迎应届毕业生和初阶职场人士。
A50: 513 | B50: CTA Card | C50: 从工作签证到初期住所，全程日语协助。安心转移到异国生活。 | D50: 从工作签证到初期住所，全程中文协助。安心转移到异国生活。 | E50: 工作签证申请、住所安排、各项手续日语全程协助。 | F50: 工作签证申请、住所安排、各项手续中文全程协助。
A51: 519 | B51: CTA Card | C51: 非正式面试，就是了解情况。用日语或中文提问都可以。 | D51: 非正式面试，就是了解情况。用日语或中文提问都可以。 | E51: 非正式面试，就是友好沟通。用日语或中文都没问题。 | F51: 非正式面试，就是友好沟通。用中文都没问题。

Sheet daily-life-malaysia
A1: Field | B1: Value
A2: Page URL | B2: https://tpmyandtpth.github.io/MLP/daily-life-malaysia.html
A3: Page Title (EN) | B3: Daily Life Malaysia
A4: Page Title (CN) | B4: 当地生活 | TP招聘 马来西亚·泰国
A5: Created Date | B5: 2026-01-27
A6: Translator | B6: Claude AI
A7: Review Date | B7: (to be filled)
A8: Reviewer Name | B8: (to be filled)
A9: Review Status | B9: ⬜ Pending
A10: Version | B10: v1.0
A13: Content Review Table
A15: Line # | B15: Section | C15: Local Mandarin (Mixed English) | D15: Local Comment | E15: Native Mandarin | F15: Native Comment
A16: 287 | B16: Lang Toggle | C16: 🇲🇾 本地华人 | D16: 🇲🇾 本地华人 | E16: 🇲🇾 本地华人 | F16: 🇲🇾 本地华人
A17: 288 | B17: Lang Toggle | C17: 🌏 海外华人 | D17: 🌏 海外华人 | E17: 🌏 海外华人 | F17: 🌏 海外华人
A18: 310 | B18: Header Nav | C18: Home | D18: 首页 | E18: 首页 | F18: 首页
A19: 311 | B19: Header Nav | C19: About TP | D19: 关于TP | E19: 关于TP | F19: 关于TP
A20: 312 | B20: Header Nav | C20: Benefits | D20: 薪资待遇 | E20: 薪资福利 | F20: 薪资福利
A21: 313 | B21: Header Nav | C21: Hiring Process | D21: 招聘流程 | E21: 招聘流程 | F21: 招聘流程
A22: 316 | B22: Header Nav | C22: Visa Support | D22: 工作签证 | E22: 签证支持 | F22: 签证支持
A23: 317 | B23: Header Nav | C23: Apply Now | D23: 立即申请 | E23: 立即申请 | F23: 立即申请
A24: 336 | B24: Brand Tagline | C24: Malaysia·Thailand | D24: Malaysia·Thailand | E24: 马来西亚·泰国 | F24: 马来西亚·泰国
A25: 355 | B25: Hero H1 | C25: 当地Life（Food·Transport·住所）/ Daily Life in Malaysia | D25: 本地生活（饮食 · 交通 · 住宿） / 马来西亚日常生活 | E25: 当地生活（餐饮·交通·住所）/ Daily Life in Malaysia | F25: 本地生活（饮食 · 交通 · 住宿） / 马来西亚日常生活
A26: 358 | B26: Hero P | C26: Compare China更"有余裕"的life可以feel的country，Malaysia。这里，food、transport、住所、medical、weekend到，life的全貌introduce。 | D26: 相比中国节奏较快的生活，马来西亚整体生活更轻松和余裕。在这里，从饮食、交通、住宿、医疗到周末休闲，都能感受到相对舒适、自在的生活方式。本篇将带你了解在马来西亚的日常生活样貌。 | E26: 比中国更"有余裕"的生活可以感受的国家，马来西亚。这里，餐饮、交通、住所、医疗、周末到，生活的全貌介绍。 | F26: 相比中国节奏较快的生活，马来西亚整体生活更轻松和余裕。在这里，从饮食、交通、住宿、医疗到周末休闲，都能感受到相对舒适、自在的生活方式。本篇将带你了解在马来西亚的日常生活样貌。
A27: 363 | B27: Hero CTA | C27: View Jobs | D27: 查看工作机会 | E27: 查看职位 | F27: 查看工作机会
... A121: 642 | B121: Floating | C121: Casual Chat | D121: 休闲面谈 | E121: 休闲面谈 | F121: 休闲面谈

Sheet hiring-process
A1: Page | B1: hiring-process.html
A2: Title | B2: 招聘流程
A3: URL | B3: https://tpmyandtpth.github.io/MLP/hiring-process.html
A4: Items | B4: 49
A5: Status | B5: ⬜ Pending
A6: Last Updated | B6: 2026-01-27
A8: # | B8: Section | C8: Local Mandarin (Mixed English) | D8: Local Comment | E8: Native Mandarin | F8: Native Comment
A9: 1 | B9: Nav | C9: 招聘流程 | D9: =IFERROR(_xlfn.XLOOKUP(C9,index.html!C:C,index.html!D:D)," ") | E9: 招聘流程
A10: 2 | B10: Hero | C10: 招聘流程 | E10: 招聘流程
A11: 3 | B11: Hero | C11: 我们的中文团队会一路陪伴你。从申请到入职，全程关怀和支持。 | E11: 华语招聘团队全程协助。从投递简历到成功入职，每一步都有专业指导。
A12: 4 | B12: Hero CTA | C12: 查看职位 | E12: 查看职位
A13: 5 | B13: Hero CTA | C13: 轻松对话 | E13: 轻松对话
A14: 6 | B14: Hero CTA | C14: 签证支持 | E14: 签证支持
A15: 7 | B15: Card | C15: 面试次数 | E15: 面试次数
A16: 8 | B16: Card | C16: 2-3轮 | E16: 2-3轮
A17: 9 | B17: Card | C17: 所需时间 | E17: 所需时间
A18: 10 | B18: Card | C18: 面试工具 | E18: 面试工具
A19: 11 | B19: Card | C19: Microsoft Teams（会发送链接给你）。准备好安静的环境和稳定网络。 | E19: Microsoft Teams（发送链接）。需要稳定网络和安静环境。
A20: 12 | B20: Section | C20: 招聘流程（标准步骤） | E20: 招聘流程（标准步骤）
A21: 13 | B21: Section | C21: 实际流程可能因项目而有调整。 | E21: 具体步骤因项目可能有所不同。
... A57: 49 | B57: Floating | C57: 轻松对话 | E57: 轻松对话

Sheet office-environment
A1: Column1 | B1: Column2
A2: Page | B2: office-environment.html
A3: Title | B3: 办公环境
A4: URL | B4: https://tpmyandtpth.github.io/MLP/office-environment.html
A5: Items | B5: 89
A6: Status | B6: ⬜ Pending
A7: Last Updated | B7: 2026-01-27
A8: # | B8: Section | C8: Local Mandarin (Mixed English) | D8: Local Comment | E8: Native Mandarin | F8: Native Comment
A9: 1 | B9: Lang Toggle | C9: 🇲🇾 本地华人 | D9: =IFERROR(_xlfn.XLOOKUP(C9,index.html!C:C,index.html!D:D)," ") -> 0 | E9: 🇲🇾 本地华人
A10: 2 | B10: Lang Toggle | C10: 🌏 海外华人 | D10: =IFERROR(_xlfn.XLOOKUP(C10,index.html!C:C,index.html!D:D)," ") -> 0 | E10: 🌏 海外华人
A11: 3 | B11: Nav | C11: Malaysia·Thailand | D11: =IFERROR(_xlfn.XLOOKUP(C11,index.html!C:C,index.html!D:D)," ") | E11: 马来西亚·泰国
A12: 4 | B12: Nav | C12: Home | D12: =IFERROR(_xlfn.XLOOKUP(C12,index.html!C:C,index.html!D:D)," ") | E12: 首页
A13: 5 | B13: Nav | C13: About TP | D13: =IFERROR(_xlfn.XLOOKUP(C13,index.html!C:C,index.html!D:D)," ") | E13: 关于TP
A14: 6 | B14: Nav | C14: Benefits | D14: =IFERROR(_xlfn.XLOOKUP(C14,index.html!C:C,index.html!D:D)," ") | E14: 薪资福利
A15: 7 | B15: Nav | C15: Hiring Process | D15: =IFERROR(_xlfn.XLOOKUP(C15,index.html!C:C,index.html!D:D)," ") | E15: 招聘流程
A16: 8 | B16: Nav | C16: Visa Support | D16: =IFERROR(_xlfn.XLOOKUP(C16,index.html!C:C,index.html!D:D)," ") | E16: 签证支持
A17: 9 | B17: Nav | C17: Apply Now | D17: =IFERROR(_xlfn.XLOOKUP(C17,index.html!C:C,index.html!D:D)," ") -> 立即申请 | E17: 立即申请
A18: 10 | B18: Nav | C18: Office | D18: =IFERROR(_xlfn.XLOOKUP(C18,index.html!C:C,index.html!D:D)," ") | E18: 办公环境
A19: 11 | B19: Hero | C19: 办公环境 / Office & Work Environment | D19: =IFERROR(_xlfn.XLOOKUP(C19,index.html!C:C,index.html!D:D)," ") | E19: 办公环境 / Office & Work Environment
A20: 12 | B20: Hero | C20: Focus、交流、learning共存的comfortable和safe的workspace。 KL／Penang／Bangkok的office facility和周边environment用photo介绍。 | D20: =IFERROR(_xlfn.XLOOKUP(C20,index.html!C:C,index.html!D:D)," ") | E20: 专注、交流、学习共存的舒适和安全的工作空间。 KL／槟城／曼谷的办公设施和周边环境用照片介绍。
... A97: 89 | B97: Lightbox | C97: Close | D97: =IFERROR(_xlfn.XLOOKUP(C97,index.html!C:C,index.html!D:D)," ") | E97: 关闭

Sheet open-jobs
A1: Column1 | B1: Column2
A2: Page | B2: open-jobs.html
A3: Title | B3: 查看职位
A4: URL | B4: https://tpmyandtpth.github.io/MLP/open-jobs.html
A5: Items | B5: 62
A6: Status | B6: ⬜ Pending
A7: Last Updated | B7: 2026-01-27
A8: # | B8: Section | C8: Local Mandarin (Mixed English) | D8: Local Comment | E8: Native Mandarin | F8: Native Comment
A9: 1 | B9: Nav | C9: 查看职位 | D9: =IFERROR(_xlfn.XLOOKUP(C9,index.html!C:C,index.html!D:D)," ") | E9: 查看职位
A10: 2 | B10: Hero | C10: 查看职位 | D10: =IFERROR(_xlfn.XLOOKUP(C10,index.html!C:C,index.html!D:D)," ") | E10: 查看职位
A11: 3 | B11: Hero | C11: 华语职位欢迎。勤务地包括吉隆坡、槟城、曼谷。提供工作签证和搬迁支持。 | D11: 中文空缺热招中！office at Kuala Lumpur, Penang & Bangkok. 搬迁补助可额外申请 | E11: 华语岗位热招中。工作地点覆盖吉隆坡、槟城、曼谷。包含签证和搬迁协助。
A12: 4 | B12: Hero CTA | C12: 查看薪资福利 | D12: 查看薪资待遇 | E12: 查看薪资福利
A13: 5 | B13: Hero CTA | C13: 了解招聘流程 | D13: =IFERROR(_xlfn.XLOOKUP(C13,index.html!C:C,index.html!D:D)," ") | E13: 了解招聘流程
A14: 6 | B14: Hero CTA | C14: 预约轻松对话 | D14: 预约线上面试 | E14: 预约轻松对话 | F14: 预约线上面试
A15: 7 | B15: Job Card 1 | C15: 客户服务代表 | D15: 客服 (CS) | E15: 客户服务代表 | F15: 客服岗位
A16: 8 | B16: Job Card 1 | C16: 招聘中 | D16: =IFERROR(_xlfn.XLOOKUP(C16,index.html!C:C,index.html!D:D)," ") | E16: 招聘中
A17: 9 | B17: Job Card 1 | C17: 地点：吉隆坡 | D17: =IFERROR(_xlfn.XLOOKUP(C17,index.html!C:C,index.html!D:D)," ") | E17: 地点：吉隆坡
A18: 10 | B18: Job Card 1 | C18: 语言：中文/日语 | D18: =IFERROR(_xlfn.XLOOKUP(C18,index.html!C:C,index.html!D:D)," ") | E18: 语言：中文/日语
A19: 11 | B19: Job Card 1 | C19: 类型：正式员工 | D19: =IFERROR(_xlfn.XLOOKUP(C19,index.html!C:C,index.html!D:D)," ") | E19: 类型：正式员工
A20: 12 | B20: Job Card 1 | C20: 班次：轮班制 | D20: =IFERROR(_xlfn.XLOOKUP(C20,index.html!C:C,index.html!D:D)," ") | E20: 班次：轮班制
A21: 13 | B21: Job Card 1 | C21: 为大型电商平台客户提供华语支持。 | D21: =IFERROR(_xlfn.XLOOKUP(C21,index.html!C:C,index.html!D:D)," ") | E21: 为全球电商平台用户提供华语客服。
A22: 14 | B22: Job Card 1 | C22: 处理订单、配送、退货等咨询。 | D22: =IFERROR(_xlfn.XLOOKUP(C22,index.html!C:C,index.html!D:D)," ") | E22: 处理订单、配送、退货等相关事务。
A23: 15 | B23: Job Card 1 | C23: 通过电话、邮件、聊天提供支持。 | D23: =IFERROR(_xlfn.XLOOKUP(C23,index.html!C:C,index.html!D:D)," ") | E23: 通过多渠道提供客户支持。
A24: 16 | B24: Job Card 1 | C24: 中文流利（书写和交流） | D24: =IFERROR(_xlfn.XLOOKUP(C24,index.html!C:C,index.html!D:D)," ") | E24: 中文流利（书写和交流）
A25: 17 | B25: Job Card 1 | C25: 大专或以上学历 | D25: minimum SPM | E25: 大专或以上学历
A26: 18 | B26: Job Card 1 | C26: 欢迎无经验应聘者 | D26: =IFERROR(_xlfn.XLOOKUP(C26,index.html!C:C,index.html!D:D)," ") | E26: 欢迎无经验应聘者
A27: 19 | B27: Job Card 1 | C27: 能适应轮班制工作 | D27: =IFERROR(_xlfn.XLOOKUP(C27,index.html!C:C,index.html!D:D)," ") | E27: 能适应轮班制工作
A28: 20 | B28: Job Card 1 | C28: 客服经验者优先 | D28: =IFERROR(_xlfn.XLOOKUP(C28,index.html!C:C,index.html!D:D)," ") | E28: 客服经验者优先
A29: 21 | B29: Job Card 1 | C29: 轻松对话 | D29: 线上面试 | E29: 轻松对话 | F29: 线上面试
A30: 22 | B30: Job Card 1 | C30: 了解流程 | D30: =IFERROR(_xlfn.XLOOKUP(C30,index.html!C:C,index.html!D:D)," ") | E30: 了解流程
A31: 23 | B31: Job Card 1 | C31: 立即申请 | D31: =IFERROR(_xlfn.XLOOKUP(C31,index.html!C:C,index.html!D:D)," ") | E31: 立即申请
A32: 24 | B32: Job Card 2 | C32: 金融支持顾问 | D32: 金融支持专员 | E32: 金融支持顾问 | F32: 金融支持专员
A33: 25 | B33: Job Card 2 | C33: 招聘中 | D33: =IFERROR(_xlfn.XLOOKUP(C33,index.html!C:C,index.html!D:D)," ") | E33: 招聘中
A34: 26 | B34: Job Card 2 | C34: 地点：槟城 | D34: =IFERROR(_xlfn.XLOOKUP(C34,index.html!C:C,index.html!D:D)," ") | E34: 地点：槟城
A35: 27 | B35: Job Card 2 | C35: 语言：中文主要 | D35: =IFERROR(_xlfn.XLOOKUP(C35,index.html!C:C,index.html!D:D)," ") | E35: 语言：中文主要
A36: 28 | B36: Job Card 2 | C36: 类型：正式员工 | D36: =IFERROR(_xlfn.XLOOKUP(C36,index.html!C:C,index.html!D:D)," ") | E36: 类型：正式员工
A37: 29 | B37: Job Card 2 | C37: 班次：轮班制 | D37: =IFERROR(_xlfn.XLOOKUP(C37,index.html!C:C,index.html!D:D)," ") | E37: 班次：轮班制
A38: 30 | B38: Job Card 2 | C38: 为在线支付用户提供一级支持。 | D38: 为全球用户提供一级支持服务。 | E38: 为全球在线支付用户提供一级支持。 | F38: 为全球用户提供一级支持服务。
A39: 31 | B39: Job Card 2 | C39: 处理账户、交易、技术问题。 | D39: =IFERROR(_xlfn.XLOOKUP(C39,index.html!C:C,index.html!D:D)," ") | E39: 处理账户查询、交易问题、技术支持。
A40: 32 | B40: Job Card 2 | C40: 记录和升级客户问题到相关部门。 | D40: =IFERROR(_xlfn.XLOOKUP(C40,index.html!C:C,index.html!D:D)," ") | E40: 记录详情并适当升级复杂案例。
A41: 33 | B41: Job Card 2 | C41: 中文和英文流利 | D41: =IFERROR(_xlfn.XLOOKUP(C41,index.html!C:C,index.html!D:D)," ") | E41: 中文和英文流利
A42: 34 | B42: Job Card 2 | C42: 客服或财务背景优先 | D42: =IFERROR(_xlfn.XLOOKUP(C42,index.html!C:C,index.html!D:D)," ") | E42: 客服或财务背景优先
A43: 35 | B43: Job Card 2 | C43: Windows基础操作能力 | D43: =IFERROR(_xlfn.XLOOKUP(C43,index.html!C:C,index.html!D:D)," ") | E43: Windows基础操作能力
A44: 36 | B44: Job Card 2 | C44: 强沟通和问题解决能力 | D44: =IFERROR(_xlfn.XLOOKUP(C44,index.html!C:C,index.html!D:D)," ") | E44: 强沟通和问题解决能力
A45: 37 | B45: Job Card 2 | C45: 欢迎初入职场者 | D45: =IFERROR(_xlfn.XLOOKUP(C45,index.html!C:C,index.html!D:D)," ") | E45: 欢迎初入职场者
A46: 38 | B46: Job Card 2 | C46: 轻松对话 | D46: 线上面试 | E46: 轻松对话 | F46: 线上面试
A47: 39 | B47: Job Card 2 | C47: 了解流程 | D47: =IFERROR(_xlfn.XLOOKUP(C47,index.html!C:C,index.html!D:D)," ") | E47: 了解流程
A48: 40 | B48: Job Card 2 | C48: 立即申请 | D48: =IFERROR(_xlfn.XLOOKUP(C48,index.html!C:C,index.html!D:D)," ") | E48: 立即申请
A49: 41 | B49: Job Card 3 | C49: 销售代表 | D49: =IFERROR(_xlfn.XLOOKUP(C49,index.html!C:C,index.html!D:D)," ") | E49: 销售代表
A50: 42 | B50: Job Card 3 | C50: 招聘中 | D50: =IFERROR(_xlfn.XLOOKUP(C50,index.html!C:C,index.html!D:D)," ") | E50: 招聘中
A51: 43 | B51: Job Card 3 | C51: 地点：曼谷 | D51: =IFERROR(_xlfn.XLOOKUP(C51,index.html!C:C,index.html!D:D)," ") | E51: 地点：曼谷
A52: 44 | B52: Job Card 3 | C52: 语言：中文/英文 | D52: =IFERROR(_xlfn.XLOOKUP(C52,index.html!C:C,index.html!D:D)," ") | E52: 语言：中文/英文
A53: 45 | B53: Job Card 3 | C53: 类型：正式员工 | D53: =IFERROR(_xlfn.XLOOKUP(C53,index.html!C:C,index.html!D:D)," ") | E53: 类型：正式员工
A54: 46 | B54: Job Card 3 | C54: 班次：日班 | D54: Weekday only | E54: 班次：日班
A55: 47 | B55: Job Card 3 | C55: 为中国市场销售云安全解决方案。 | D55: =IFERROR(_xlfn.XLOOKUP(C55,index.html!C:C,index.html!D:D)," ") | E55: 销售企业云安全解决方案给亚太地区。
A56: 48 | B56: Job Card 3 | C56: 识别商机并进行商务洽谈。 | D56: =IFERROR(_xlfn.XLOOKUP(C56,index.html!C:C,index.html!D:D)," ") | E56: 发现潜在客户并推进销售机会。
A57: 49 | B57: Job Card 3 | C57: 使用CRM系统管理客户关系。 | D57: =IFERROR(_xlfn.XLOOKUP(C57,index.html!C:C,index.html!D:D)," ") | E57: 使用销售工具管理客户信息和活动。
A58: 50 | B58: Job Card 3 | C58: 中文和英文流利 | D58: =IFERROR(_xlfn.XLOOKUP(C58,index.html!C:C,index.html!D:D)," ") | E58: 中文和英文流利
A59: 51 | B59: Job Card 3 | C59: 销售、市场推广或客户管理经验 | D59: =IFERROR(_xlfn.XLOOKUP(C59,index.html!C:C,index.html!D:D)," ") | E59: 销售、市场推广或客户管理经验
A60: 52 | B60: Job Card 3 | C60: 自驱力强、独立工作能力强 | D60: =IFERROR(_xlfn.XLOOKUP(C60,index.html!C:C,index.html!D:D)," ") | E60: 自驱力强、独立工作能力强
A61: 53 | B61: Job Card 3 | C61: 问题解决和谈判能力出色 | D61: =IFERROR(_xlfn.XLOOKUP(C61,index.html!C:C,index.html!D:D)," ") | E61: 问题解决和谈判能力出色
A62: 54 | B62: Job Card 3 | C62: 对数字营销感兴趣 | D62: =IFERROR(_xlfn.XLOOKUP(C62,index.html!C:C,index.html!D:D)," ") | E62: 对数字营销感兴趣
A63: 55 | B63: Job Card 3 | C63: 轻松对话 | D63: 线上面试 | E63: 轻松对话 | F63: 线上面试
A64: 56 | B64: Job Card 3 | C64: 了解流程 | D64: =IFERROR(_xlfn.XLOOKUP(C64,index.html!C:C,index.html!D:D)," ") | E64: 了解流程
A65: 57 | B65: Job Card 3 | C65: 立即申请 | D65: =IFERROR(_xlfn.XLOOKUP(C65,index.html!C:C,index.html!D:D)," ") | E65: 立即申请
A66: 58 | B66: Helper CTA | C66: 不确定适合哪个职位？ | D66: =IFERROR(_xlfn.XLOOKUP(C66,index.html!C:C,index.html!D:D)," ") | E66: 不确定适合哪个职位？
A67: 59 | B67: Helper CTA | C67: 预约轻松对话（30分钟）咨询任何问题。 | D67: 线上面试（30分钟）咨询任何问题 | E67: 预约轻松对话（30分钟）咨询任何问题。 | F67: 线上面试（30分钟）咨询任何问题
A68: 60 | B68: Helper CTA | C68: 预约对话 | D68: =IFERROR(_xlfn.XLOOKUP(C68,index.html!C:C,index.html!D:D)," ") | E68: 预约对话
A69: 61 | B69: Floating | C69: 立即申请 | D69: =IFERROR(_xlfn.XLOOKUP(C69,index.html!C:C,index.html!D:D)," ") | E69: 立即申请
A70: 62 | B70: Floating | C70: 轻松对话 | D70: 线上面试 | E70: 轻松对话 | F70: 线上面试

Sheet relocation-visa
A1: Column1 | B1: Column2
A2: Page | B2: relocation-visa.html
A3: Title | B3: 搬迁·签证支持
A4: URL | B4: https://tpmyandtpth.github.io/MLP/relocation-visa.html
A5: Items | B5: 68
A6: Status | B6: ⬜ Pending
A7: Last Updated | B7: 2026-01-27
A8: # | B8: Section | C8: Local Mandarin (Mixed English) | D8: Local Comment | E8: Native Mandarin | F8: Native Comment
A9: 1 | B9: Lang Toggle | C9: 🇲🇾 本地华人 | D9: =IFERROR(_xlfn.XLOOKUP(C9,index.html!C:C,index.html!D:D)," ") -> 0 | E9: 🇲🇾 本地华人
A10: 2 | B10: Lang Toggle | C10: 🌏 海外华人 | D10: =IFERROR(_xlfn.XLOOKUP(C10,index.html!C:C,index.html!D:D)," ") -> 0 | E10: 🌏 海外华人
A11: 3 | B11: Nav | C11: Malaysia·Thailand | D11: =IFERROR(_xlfn.XLOOKUP(C11,index.html!C:C,index.html!D:D)," ") | E11: 马来西亚·泰国
A12: 4 | B12: Nav | C12: Home | D12: 首页 | E12: 首页
A13: 5 | B13: Nav | C13: About TP | D13: 关于TP | E13: 关于TP
A14: 6 | B14: Nav | C14: Benefits | D14: 薪资待遇 | E14: 薪资福利
A15: 7 | B15: Nav | C15: Hiring Process | D15: 招聘流程 | E15: 招聘流程
A16: 8 | B16: Nav | C16: Visa Support | D16: 工作签证 | E16: 签证支持
A17: 9 | B17: Nav | C17: Apply Now | D17: =IFERROR(_xlfn.XLOOKUP(C17,index.html!C:C,index.html!D:D)," ") -> 立即申请 | E17: 立即申请
A18: 10 | B18: Hero | C18: 搬迁·签证Support / Relocation & Visa Support | D18: 搬迁补贴/工作签证支持 | E18: 搬迁·签证支持 / Relocation & Visa Support
A19: 11 | B19: Hero | C19: 第一次overseas搬迁，我们也会support你。 Work visa是company负担apply，华语staff会carefully support。Flight ticket·airport transfer·hotel的arrangement全部company来做。 ※Support内容和condition根据location不同。 | D19: =IFERROR(_xlfn.XLOOKUP(C19,index.html!C:C,index.html!D:D)," ") | E19: 第一次海外搬迁，我们也会支持你。 工作签证是公司负担申请，华语员工会细心支持。机票·机场接送·酒店的安排全部公司来做。 ※支持内容和条件根据地点不同。
A20: 12 | B20: Hero CTA | C20: View Jobs | D20: =IFERROR(_xlfn.XLOOKUP(C20,index.html!C:C,index.html!D:D)," ") | E20: 查看职位
A21: 13 | B21: Hero CTA | C21: Casual Chat | D21: =IFERROR(_xlfn.XLOOKUP(C21,index.html!C:C,index.html!D:D)," ") | E21: 休闲面谈 | F21: 咨询面谈
A22: 14 | B22: Hero CTA | C22: Benefits | D22: 福利待遇 | E22: 薪资福利
A23: 15 | B23: Highlights | C23: Support的Highlight | D23: =IFERROR(_xlfn.XLOOKUP(C23,index.html!C:C,index.html!D:D)," ") | E23: 支持的亮点
A24: 16 | B24: Card | C24: Visa费用Company负担 | D24: 公司协助申请工作签证 | E24: 签证费用公司负担
A25: 17 | B25: Card | C25: Work visa（EP）application费用company负担。从requirement document的guide到apply一贯support。 | D25: =IFERROR(_xlfn.XLOOKUP(C25,index.html!C:C,index.html!D:D)," ") | E25: 工作签证（EP）申请费用公司负担。从所需文件的指南到申请一贯支持。 | F25: 工作签证（EP）申请费用将由公司负担。所需文件的指南到提交申请一贯支持。
A26: 18 | B26: Card | C26: 目安Schedule | D26: 时间表和预期 | E26: 大概日程 | F26: 时间表和预期
A27: 19 | B27: Card | C27: 从offer到approximately 2个月issue是目安。Progress用华语随时update。 | D27: 工签从录用到完成入职需约8周时间完成。进度将实时更新。 | E27: 从录用到大约2个月发放是大概。进度用华语随时更新。 | F27: 从录用到完成入职约8周时间。进度将实时更新。
A28: 20 | B28: Card | C28: Flight·Arrival Support | D28: =IFERROR(_xlfn.XLOOKUP(C28,index.html!C:C,index.html!D:D)," ") | E28: 机票·到达支持
A29: 21 | B29: Card | C29: One-way flight ticket提供·airport transfer加上，Malaysia是arrival后hotel prepare（stay期间找住所）。 | D29: 单程机票及机场接送将由公司协助安排，马来西亚是到达后将提供一周酒店住宿。 | E29: 单程机票提供·机场接送加上，马来西亚是到达后酒店准备（住宿期间找住所）。 | F29: 单程机票及机场接送将由公司协助安排，马来西亚是到达后将提供一周酒店住宿。
A30: 22 | B30: Process | C30: 入职的Flow（Overview） | D30: 入职流程（概述） | E30: 入职流程（概述）
A31: 23 | B31: Process | C31: 根据each project的schedule progress。 | D31: 根据每个项目的日程进行。 | E31: 根据每个项目的日程进行。
A32: 24 | B32: Step | C32: Offer | D32: =IFERROR(_xlfn.XLOOKUP(C32,index.html!C:C,index.html!D:D)," ") | E32: 录用
A33: 25 | B33: Step | C33: Condition·入职timing调整 | D33: 入职日期调整 | E33: 条件·入职时间调整 | F33: 入职条件和时间调整
A34: 26 | B34: Step | C34: Document Guide | D34: 文件提交指南 | E34: 文件指南
A35: 27 | B35: Step | C35: Requirement document提交 | D35: 所需文件提交 | E35: 所需文件提交
A36: 28 | B36: Step | C36: Visa Apply | D36: 签证申请 | E36: 签证申请
A37: 29 | B37: Step | C37: Specialist team apply（company负担） | D37: 专业团队协助申请 | E37: 专业团队申请 | F37: 专业团队协助申请
A38: 30 | B38: Step | C38: Flight Booking | D38: 机票预订 | E38: 机票预订
A39: 31 | B39: Step | C39: One-way ticket·arrival date confirm | D39: 单程机票·到达日期确认 | E39: 单程机票·到达日期确认
A40: 32 | B40: Step | C40: Arrival Support | D40: 入境抵达支持 | E40: 到达支持 | F40: 入境抵达支持
A41: 33 | B41: Step | C41: Airport transfer·hotel | D41: 机场接送·酒店 | E41: 机场接送·酒店
A42: 34 | B42: Step | C42: Training Start | D42: =IFERROR(_xlfn.XLOOKUP(C42,index.html!C:C,index.html!D:D)," ") | E42: 培训开始
A43: 35 | B43: Step | C43: 入职procedure·training | D43: 入职手续及培训 | E43: 入职手续·培训 | F43: 入职手续及培训
A44: 36 | B44: FAQ Section | C44: Work Visa和Arrival后Support | D44: 工作签证和到达后支持 | E44: 工作签证和到达后支持
A45: 37 | B45: FAQ | C45: Work Visa（Employment Pass, EP） | D45: =IFERROR(_xlfn.XLOOKUP(C45,index.html!C:C,index.html!D:D)," ") | E45: 工作签证（Employment Pass, EP）
A46: 38 | B46: FAQ | C46: Application费用：Company负担 | D46: 申请费用 （company Sponsor) | E46: 申请费用：公司负担
A47: 39 | B47: FAQ | C47: Issue目安：从offer approximately 2个月 | D47: Offer 发出至签证完成需要越8周时间完成 | E47: 发放大概：从录用大约2个月 | F47: 录取书发出至签证完成需要越8周时间完成
A48: 40 | B48: FAQ | C48: 华语support：Requirement document guide·application progress share | D48: 华语支持：所需文件指南· 申请进度将实时更新。 | E48: 华语支持：所需文件指南·申请进度分享 | F48: 华语支持：所需文件指南·申请进度将实时更新。
A49: 41 | B49: FAQ | C49: ※Detail根据position·country规定不同。Latest info在selection时guide。 | D49: ※详细根据职位·国家规定不同。最新信息在选拔时指南。 | E49: ※详细根据职位·国家规定不同。最新信息在选拔时指南。
A50: 42 | B50: FAQ | C50: Family帯同（Dependent Pass） | D50: 家属签证（Dependent Pass） | E50: 家属同行（Dependent Pass） | F50: 家属签证（Dependent Pass）
A51: 43 | B51: FAQ | C51: Work visa（EP）取得后，配偶·孩子向的Dependent Pass apply可能。华语medical institution和华语school/community也有，带family relocate的example也很多。 | D51: 工作签证（EP）取得后，配偶及孩子家属可提交签证申请。本地提供华语医疗机构和华语学校/社区，带家属搬迁的例子也很多。 | E51: 工作签证（EP）取得后，配偶及孩子家属可提交签证申请。本地提供华语医疗机构和华语学校/社区，带家属搬迁的例子也很多。
A52: 44 | B52: FAQ | C52: Flight·Arrival时的Support | D52: 到达马来西亚的安排支持 | E52: 机票·到达时的支持 | F52: 抵达马拉西亚的安排支持
A53: 45 | B53: FAQ | C53: One-way flight ticket提供（入职时） | D53: 单程机票将提供（入职时） | E53: 单程机票提供（入职时） | F53: 单程机票将提供（入职时）
A54: 46 | B54: FAQ | C54: Airport到公司指定hotel的transfer（Malaysia） | D54: 机场到公司指定酒店的接送（马来西亚） | E54: 机场到公司指定酒店的接送（马来西亚）
A55: 47 | B55: FAQ | C55: Arrival后的hotel：Stay期间找住所 | D55: 到达后的酒店：住宿期间找住所 | E55: 到达后的酒店：住宿期间找住所
A56: 48 | B56: FAQ | C56: ※Interview时guide。 | D56: Interview Tips | E56: ※面试指南。 | F56: 面试指南
A57: 49 | B57: Life Section | C57: 住所·Life Set Up | D57: 住所·生活建立 | E57: 住所·生活建立 | F57: 住所·生活建立
A58: 50 | B58: Life Section | C58: Real estate agent的introduction我们会做。 | D58: 提供搬迁协助 - 房产中介/ 平台 | E58: 房产中介的介绍我们会做。 | F58: 提供搬迁协助 - 房产中介/ 平台
A59: 51 | B59: Card | C59: 住所的General Image（KL/Penang） | D59: 住所的一般情况信息（KL/槟城） | E59: 住所的一般情况（KL/槟城） | F59: 住所的一般情况信息（KL/槟城）
A60: 52 | B60: Card | C60: Pool·Gym·24h Security付的condo是general。Furniture appliance付，可以immediately move in的property很多。 | D60: 本地公寓一般公共设有泳池，健身房及确保24小时安保系统。大部分出租房间都可以拎包入住。 | E60: 泳池·健身房·24小时保安付的公寓是一般。家具家电付，可以立即入住的房产很多。 | F60: 本地公寓一般公共设有泳池，健身房 及确保24小时安保系统。大部分出租家具可以拎包入住。
A61: 53 | B61: Pill | C61: Furniture·Appliance付 | D61: 基础家私和大件电器 | E61: 家具·家电付 | F61: 基础家私和大件电器
A62: 54 | B62: Pill | C62: Pool/Gym | D62: Swimming Pool/Gym | E62: 泳池/健身房
A63: 55 | B63: Pill | C63: 24h Security | D63: =IFERROR(_xlfn.XLOOKUP(C63,index.html!C:C,index.html!D:D)," ") | E63: 24小时保安 | F63: 24小时安保系统
A64: 56 | B64: Card | C64: Cost of Living目安 | D64: =IFERROR(_xlfn.XLOOKUP(C64,index.html!C:C,index.html!D:D)," ") | E64: 生活成本大概
A65: 57 | B65: Card | C65: Compare China（北京·上海），cost of living容易control，time·money·心理都会有余裕。Detail请看「城市介绍」。 | D65: 对比外国/大城市，Penang生活成本更低，时间和金钱都会有余裕。详细请看「城市介绍」。 | E65: 对比中国（北京·上海），生活成本容易控制，时间·金钱·心理都会有余裕。详细请看「城市介绍」。 | F65: 对比中国（北京·上海），马来西亚生活成本更低，时间和金钱都会有余裕。详细请看「城市介绍」。
A66: 58 | B66: Card | C66: Local Life Info | D66: =IFERROR(_xlfn.XLOOKUP(C66,index.html!C:C,index.html!D:D)," ") | E66: 当地生活信息
A67: 59 | B67: Card | C67: Chinese food店、华语medical、transport等在「Daily Life」「城市介绍」summarize了。 | D67: 大排档、中西药行、交通等在「城市介绍」有详细介绍了。 | E67: 中餐店、华语医疗、交通等在「日常生活」「城市介绍」总结了。 | F67: 平价中餐、中西药行、交通等在「城市介绍」有详细介绍。
A68: 60 | B68: Country | C68: Country·City的特色（抜粋） | D68: 马来西亚国家·城市的特色（summary） | E68: 国家·城市的特色（摘录） | F68: 马来西亚国家·城市的特色（摘录）
A69: 61 | B69: Country | C69: Malaysia（KL / Penang） | D69: =IFERROR(_xlfn.XLOOKUP(C69,index.html!C:C,index.html!D:D)," ") | E69: 马来西亚（KL / 槟城） | F69: 马来西亚（吉隆坡 / 槟城）
A70: 62 | B70: Country | C70: Multicultural English广泛通用，华语facility也complete。KL是city type，Penang是sea和nature也close。Arrival後hotel arrange（MY）。 | D70: 多元文化语言广泛通用，华语设施也完善。KL是大城市型，槟城是相较亲近大自然的城市。 | E70: 多元文化英语广泛通用，华语设施也完善。KL是城市型，槟城是海和自然也近。到达后酒店安排（马来西亚）。 | F70: 多元文化语言广泛通用，华语设施也完善。KL是大城市型，槟城是相较亲近大自然的城市。
A71: 63 | B71: Country | C71: Thailand（Bangkok） | D71: =IFERROR(_xlfn.XLOOKUP(C71,index.html!C:C,index.html!D:D)," ") | E71: 泰国（曼谷）
A72: 64 | B72: Country | C72: 华语facility·hospital非常complete。BTS/MRT移动easy，furniture付condo comfortable live。 ※Arrival后hotel arrange | D72: 本地华语设施，医疗及教育系统非常完善。 | E72: 华语设施·医院非常完善。BTS/MRT移动方便，家具付公寓舒适生活。 ※到达后酒店安排 | F72: 本地华语设施，医疗及教育系统非常完善。
A73: 65 | B73: Helper CTA | C73: 先用华语consult吧？ | D73: =IFERROR(_xlfn.XLOOKUP(C73,index.html!C:C,index.html!D:D)," ") | E73: 先用华语咨询吧？
A74: 66 | B74: Helper CTA | C74: 30分钟的Casual Chat，visa·住所·life的不安都可以解消。 马上apply的话请去Job List。 | D74: 20分钟的线上面谈，解答您签证住所，生活的疑问。 浏览职位列表，即可提交工作申请。 | E74: 30分钟的休闲面谈，签证·住所·生活的不安都可以消除。 马上申请的话请去职位列表。 | F74: 20分钟的线上面谈，解答您签证住所，生活的疑问。 浏览职位列表，即可提交工作申请。
A75: 67 | B75: Floating | C75: Apply Now | D75: =IFERROR(_xlfn.XLOOKUP(C75,index.html!C:C,index.html!D:D)," ") -> 立即申请 | E75: 立即申请
A76: 68 | B76: Floating | C76: Casual Chat | D76: 线上面试 | E76: 休闲面谈 | F76: 线上面试

Sheet salary-and-benefits
A1: Column1 | B1: Column2
A2: Page | B2: salary-and-benefits.html
A3: Title | B3: 薪资福利
A4: URL | B4: https://tpmyandtpth.github.io/MLP/salary-and-benefits.html
A5: Items | B5: 57
A6: Status | B6: ⬜ Pending
A7: Last Updated | B7: 2026-01-27
A8: # | B8: Section | C8: Local Mandarin (Mixed English) | D8: Local Comment | E8: Native Mandarin | F8: Native Comment
A9: 1 | B9: Lang Toggle | C9: 🇲🇾 本地华人 | D9: =IFERROR(_xlfn.XLOOKUP(C9,index.html!C:C,index.html!D:D)," ") -> 0 | E9: 🇲🇾 本地华人
A10: 2 | B10: Lang Toggle | C10: 🌏 海外华人 | D10: =IFERROR(_xlfn.XLOOKUP(C10,index.html!C:C,index.html!D:D)," ") -> 0 | E10: 🌏 海外华人
A11: 3 | B11: Nav | C11: Malaysia·Thailand | D11: =IFERROR(_xlfn.XLOOKUP(C11,index.html!C:C,index.html!D:D)," ") | E11: 马来西亚·泰国
A12: 4 | B12: Nav | C12: Home | D12: =IFERROR(_xlfn.XLOOKUP(C12,index.html!C:C,index.html!D:D)," ") | E12: 首页
A13: 5 | B13: Nav | C13: About TP | D13: =IFERROR(_xlfn.XLOOKUP(C13,index.html!C:C,index.html!D:D)," ") | E13: 关于TP
A14: 6 | B14: Nav | C14: Benefits | D14: =IFERROR(_xlfn.XLOOKUP(C14,index.html!C:C,index.html!D:D)," ") | E14: 薪资福利
A15: 7 | B15: Nav | C15: Hiring Process | D15: =IFERROR(_xlfn.XLOOKUP(C15,index.html!C:C,index.html!D:D)," ") | E15: 招聘流程
A16: 8 | B16: Nav | C16: Visa Support | D16: =IFERROR(_xlfn.XLOOKUP(C16,index.html!C:C,index.html!D:D)," ") | E16: 签证支持
A17: 9 | B17: Nav | C17: Apply Now | D17: =IFERROR(_xlfn.XLOOKUP(C17,index.html!C:C,index.html!D:D)," ") -> 立即申请 | E17: 立即申请
A18: 10 | B18: Hero | C18: 薪资福利 / Salary & Benefits | D18: =IFERROR(_xlfn.XLOOKUP(C18,index.html!C:C,index.html!D:D)," ") | E18: 薪资福利 / Salary & Benefits
A19: 11 | B19: Hero | C19: 为了让你可以安心start overseas career，我们prepare了fair的evaluation和complete的benefits、relocation support。 ※Position·location不同detail会在offer letter里面告诉你。 | D19: =IFERROR(_xlfn.XLOOKUP(C19,index.html!C:C,index.html!D:D)," ") | E19: 为了让你可以安心开启海外职业，我们准备了公正的评估和完善的福利、搬迁支持。 ※职位·地点不同详细会在录用通知书里面告诉你。
A20: 12 | B20: Hero CTA | C20: View Jobs | D20: =IFERROR(_xlfn.XLOOKUP(C20,index.html!C:C,index.html!D:D)," ") | E20: 查看职位
... A64: 56 | B64: Floating | C64: Apply Now | D64: =IFERROR(_xlfn.XLOOKUP(C64,index.html!C:C,index.html!D:D)," ") -> 立即申请 | E64: 立即申请
A65: 57 | B65: Floating | C65: Casual Chat | D65: 初步线上面谈 | E65: 休闲面谈 | F65: 初步线上面谈

Sheet ta-team.html
A1: Column1 | B1: Column2
A2: Page URL: | B2: https://tpmyandtpth.github.io/MLP/ta-team.html
A3: Page Title (Local): | B3: 认识我们的TA Team
A4: Page Title (Expat): | B4: 认识招聘团队
A5: Extraction Date: | B5: 2026-01-27
A6: Review Status: | B6: ⬜ Pending
A7: Total Items: | B7: 78
A8: Line # | B8: Section | C8: Local Mandarin (Mixed English) | D8: Local Comment | E8: Native Mandarin | F8: Native Comment
A9: 1 | B9: Content | C9: Malaysia·Thailand | D9: Malaysia·Thailand | E9: 马来西亚·泰国 | F9: 马来西亚·泰国
A10: 2 | B10: Nav | C10: Home | D10: 首页 | E10: 首页 | F10: 首页
A11: 3 | B11: Content | C11: About TP | D11: 关于TP | E11: 关于TP | F11: 关于TP
A12: 4 | B12: Content | C12: Benefits | D12: 薪资待遇 | E12: 薪资福利 | F12: 薪资福利
A13: 5 | B13: Content | C13: Hiring Process | D13: 招聘流程 | E13: 招聘流程 | F13: 招聘流程
A14: 6 | B14: Content | C14: Visa Support | D14: 工作签证 | E14: 签证支持 | F14: 签证支持
A15: 7 | B15: Content | C15: Apply Now | D15: =IFERROR(_xlfn.XLOOKUP(C15,index.html!C:C,index.html!D:D)," ") -> 立即申请 | E15: 立即申请 | F15: 立即申请
A16: 8 | B16: Team Section | C16: TA Team | D16: 招聘团队 | E16: 招聘团队 | F16: 招聘团队
A17: 9 | B17: Hero | C17: 认识我们的TA Team | D17: 认识我们的招聘团队 | E17: 认识招聘团队 | F17: 认识招聘团队
A18: 10 | B18: Hero | C18: 从apply到入职，华语全程support。第一次overseas job也没问题，我们会一步一步帮你settle down。 | D18: 从申请到入职，全程华语协助。第一次到海外工作也不用担心，我们会一步一步地协助您 | E18: 从申请到入职，华语全程支持。第一次海外工作也没问题，我们会一步一步帮你安顿下来。 | F18: 从申请到入职，全程华语协助。第一次到海外工作也不用担心，我们会一步一步地协助您
A19: 11 | B19: Hero | C19: View Open Jobs | D19: 查看工作机会 | E19: 查看职位 | F19: 查看工作机会
A20: 12 | B20: Hero | C20: Book Casual Chat | D20: 预约线上面谈 | E20: 预约休闲面谈 | F20: 预约线上面谈
A21: 13 | B21: Content | C21: LINE最新Info | D21: LINE最新Info | E21: LINE最新信息 | F21: LINE最新消息
A22: 14 | B22: Nav | C22: Our Mission | D22: 我们的使命 | E22: 我们的使命 | F22: 我们的使命
A23: 15 | B23: Mission | C23: Team Members | D23: 团队成员 | E23: 团队成员 | F23: 团队成员
A24: 16 | B24: Mission | C24: Support Flow | D24: 协助流程 | E24: 支持流程 | F24: 协助流程
A25: 17 | B25: Team Section | C25: Contact Us | D25: 联系我们 | E25: 联系我们 | F25: 联系我们
A26: 18 | B26: Card | C26: 华语全程Support | D26: 全程华语Support | E26: 华语全程支持 | F26: 全程华语协助
A27: 19 | B27: Card | C27: 从apply到interview到visa到入职，每一个step都用华语guide你。First time overseas experience的人也完全okay！ | D27: 从申请到面试到获取签证到入职，每一个步骤都用华语指导你。第一次海外经历的人也完全没问题！ | E27: 从申请到面试到签证到入职，每一个步骤都用华语指导你。第一次海外经历的人也完全没问题！ | F27: 从申请到面试到获取签证到入职，每一个步骤都用华语指导你。第一次海外经历的人也完全没问题！
... A86: 78 | B86: Leader Profile | C86: Hello！我是TP Malaysia华语recruitment team的Kent，负责manage华语speaker和multilingual talent的hiring 🌏 之前在recruitment line做了大概10年++，handle过很多different industry的position——IT、logistics、semiconductor、infrastructure等等，从engineer、support role到management level、C-level position都有touch过。 因为之前有involve Malaysia、Singapore、Thailand、Japan、Korea、Australia、New Zealand等等country的recruitment project，所以对各国的culture和candidate background都比较familiar。我一直believe 'one size doesn't fit all'，每个candidate都deserve personalized的approach。 🌴 Private life方面，我超爱scuba diving和golf！Malaysia这边这些activity都超affordable，生活quality真的很chill！Weekend去diving spot或者golf course relax一下，简直太perfect了。 ✉️ 给candidates的话： Overseas转职是big challenge，但也是expand你possibilities的amazing opportunity。我understand first time去new environment会有很多worries，但是我们会try our best来guide你整个selection process和local生活的info，让你可以放心apply。 很多华语speaker已经在Malaysia和Thailand start了他们的new career journey。希望我们可以sincerely support你的challenge，让它become你better future的first step。期待你的apply和enquiry！ | D86: 你好！我是TP马来西亚华语招聘团队的Kent，负责管理华语使用者和多语言人才的招聘 🌏 之前在招聘领域做了大概10年以上，处理过很多不同行业的职位——IT、物流、半导体、基础设施等等，从工程师、支持岗位到管理层、C级职位都有接触过。 因为之前有参与马来西亚、新加坡、泰国、日本、韩国、澳大利亚、新西兰等国家的招聘项目，所以对各国的文化和候选人背景都比较熟悉。我一直都相信大家都是有能力的潜力者，每个候选人都值得展现出自己出色的那一面。 🌴 私人生活方面，我超爱潜水和打高尔夫球！马来西亚这边的这些活动都超实惠，生活质量真的很好！周末去潜水或者打高尔夫球放松一下，简直太完美了。 ✉️ 给候选人的话： 海外转职是大挑战，但也是扩展你可能性的绝佳机会。我理解第一次去新环境会有很多担忧，但是我们会尽最大努力来指导你整个面试流程和当地生活的信息，让你可以安心申请。 很多华语语言者已经在马来西亚和泰国开始了他们的新职业旅程。我们希望可以真诚支持你的挑战，让它成为你更好的未来的第一步。期待你的申请和咨询！ | E86: 你好！我是TP马来西亚华语招聘团队的Kent，负责管理华语使用者和多语言人才的招聘 🌏 之前在招聘领域做了大概10年以上，处理过很多不同行业的职位——IT、物流、半导体、基础设施等等，从工程师、支持岗位到管理层、C级职位都有接触过。 因为之前有参与马来西亚、新加坡、泰国、日本、韩国、澳大利亚、新西兰等国家的招聘项目，所以对各国的文化和候选人背景都比较熟悉。我一直相信'一刀切不适合所有人'，每个候选人都值得个性化的方法。 🌴 私人生活方面，我超爱潜水和高尔夫！马来西亚这边这些活动都超实惠，生活质量真的很好！周末去潜水点或者高尔夫球场放松一下，简直太完美了。 ✉️ 给候选人的话： 海外转职是大挑战，但也是扩展你可能性的绝佳机会。我理解第一次去新环境会有很多担忧，但是我们会尽最大努力来指导你整个选拔流程和当地生活的信息，让你可以放心申请。 很多华语使用者已经在马来西亚和泰国开始了他们的新职业旅程。希望我们可以真诚支持你的挑战，让它成为你更好未来的第一步。期待你的申请和咨询！ | F86: 你好！我是TP马来西亚华语招聘团队的Kent，负责管理华语使用者和多语言人才的招聘 🌏 之前在招聘领域做了大概10年以上，处理过很多不同行业的职位——IT、物流、半导体、基础设施等等，从工程师、支持岗位到管理层、C级职位都有接触过。 因为之前有参与马来西亚、新加坡、泰国、日本、韩国、澳大利亚、新西兰等国家的招聘项目，所以对各国的文化和候选人背景都比较熟悉。我一直都相信大家都是有能力的潜力者，每个候选人都值得展现出自己出色的那一面。 🌴 私人生活方面，我超爱潜水和打高尔夫球！马来西亚这边的这些活动都超实惠，生活质量真的很好！周末去潜水或者打高尔夫球放松一下，简直太完美了。 ✉️ 给候选人的话： 海外转职是大挑战，但也是扩展你可能性的绝佳机会。我理解第一次去新环境会有很多担忧，但是我们会尽最大努力来指导你整个面试流程和当地生活的信息，让你可以安心申请。 很多华语语言者已经在马来西亚和泰国开始了他们的新职业旅程。我们希望可以真诚支持你的挑战，让它成为你更好的未来的第一步。期待你的申请和咨询！

Sheet testimonials.html
A1: Column1 | B1: Column2
A2: Page URL: | B2: https://tpmyandtpth.github.io/MLP/testimonials.html
A3: Page Title (Local): | B3: 员工心声 / Testimonials & Interview Stories
A4: Page Title (Expat): | B4: 员工心声 / 采访与故事
A5: Extraction Date: | B5: 2026-01-27
A6: Review Status: | B6: ⬜ Pending
A7: Total Items: | B7: 49
A8: Line # | B8: Section | C8: Local Mandarin (Mixed English) | D8: Local Comment | E8: Native Mandarin | F8: Native Comment
A9: 1 | B9: Nav | C9: Home | D9: =IFERROR(_xlfn.XLOOKUP(C9,index.html!C:C,index.html!D:D)," ") | E9: 首页
A10: 2 | B10: Content | C10: About TP | D10: =IFERROR(_xlfn.XLOOKUP(C10,index.html!C:C,index.html!D:D)," ") | E10: 关于TP
A11: 3 | B11: Content | C11: Benefits | D11: =IFERROR(_xlfn.XLOOKUP(C11,index.html!C:C,index.html!D:D)," ") | E11: 薪资福利
A12: 4 | B12: Content | C12: Hiring Process | D12: =IFERROR(_xlfn.XLOOKUP(C12,index.html!C:C,index.html!D:D)," ") | E12: 招聘流程
A13: 5 | B13: Content | C13: Visa Support | D13: =IFERROR(_xlfn.XLOOKUP(C13,index.html!C:C,index.html!D:D)," ") | E13: 签证支持
A14: 6 | B14: Content | C14: Apply Now | D14: =IFERROR(_xlfn.XLOOKUP(C14,index.html!C:C,index.html!D:D)," ") -> 立即申请 | E14: 立即申请
A15: 7 | B15: Hero | C15: 员工心声 / Testimonials & Interview Stories | D15: =IFERROR(_xlfn.XLOOKUP(C15,index.html!C:C,index.html!D:D)," ") | E15: 员工心声 / 采访与故事
A16: 8 | B16: Hero | C16: "Overseas工作"的senior们的real experience。通过video、工作体验、interview，来了解一下TP的work和life吧。 | E16: "海外工作"的前辈们的真实体验。通过视频、工作体验、采访，来了解一下TP的工作和生活吧。
A17: 9 | B17: Hero | C17: View Jobs | D17: =IFERROR(_xlfn.XLOOKUP(C17,index.html!C:C,index.html!D:D)," ") | E17: 查看职位
A18: 10 | B18: Hero | C18: Book Casual Chat | D18: =IFERROR(_xlfn.XLOOKUP(C18,index.html!C:C,index.html!D:D)," ") | E18: 预约休闲面谈
A19: 11 | B19: Video Section | C19: 员工Interview（Video） | D19: =IFERROR(_xlfn.XLOOKUP(C19,index.html!C:C,index.html!D:D)," ") | E19: 员工采访（视频）
A20: 12 | B20: Video Section | C20: 通过short video介绍现场的voice | D20: =IFERROR(_xlfn.XLOOKUP(C20,index.html!C:C,index.html!D:D)," ") | E20: 通过短视频介绍现场的声音
A21: 13 | B21: Card | C21: TP员工Interview：Latest Video | D21: =IFERROR(_xlfn.XLOOKUP(C21,index.html!C:C,index.html!D:D)," ") | E21: TP员工采访：最新视频
A22: 14 | B22: Video Section | C22: Actually工作的员工的real voice | D22: =IFERROR(_xlfn.XLOOKUP(C22,index.html!C:C,index.html!D:D)," ") | E22: 实际工作的员工的真实声音
A23: 15 | B23: Video Section | C23: Watch on YouTube → | D23: =IFERROR(_xlfn.XLOOKUP(C23,index.html!C:C,index.html!D:D)," ") | E23: 在YouTube观看 →
A24: 16 | B24: Card | C24: TP员工Interview：Agent篇 | D24: =IFERROR(_xlfn.XLOOKUP(C24,index.html!C:C,index.html!D:D)," ") | E24: TP员工采访：客服专员篇
A25: 17 | B25: Video Section | C25: 在recruitment最前线active的agent的perspective | D25: =IFERROR(_xlfn.XLOOKUP(C25,index.html!C:C,index.html!D:D)," ") | E25: 在招聘最前线活跃的专员的视角
A26: 18 | B26: Card | C26: TP员工Interview：Team Leader篇 | D26: =IFERROR(_xlfn.XLOOKUP(C26,index.html!C:C,index.html!D:D)," ") | E26: TP员工采访：团队主管篇
A27: 19 | B27: Video Section | C27: 现场management·培训的real | D27: =IFERROR(_xlfn.XLOOKUP(C27,index.html!C:C,index.html!D:D)," ") | E27: 现场管理·培训的真实情况
A28: 20 | B28: Card | C28: TP员工Interview：Operations Manager篇 | D28: =IFERROR(_xlfn.XLOOKUP(C28,index.html!C:C,index.html!D:D)," ") | E28: TP员工采访：运营经理篇
... A56: 48 | B56: Card | C56: 不是selection。华语30分钟，work/life/relocation的疑问都可以consult。 | D56: =IFERROR(_xlfn.XLOOKUP(C56,index.html!C:C,index.html!D:D)," ") | E56: 不是选拔。华语30分钟，工作/生活/搬迁的疑问都可以咨询。
A57: 49 | B57: Content | C57: Book Now | E57: 立即预约

Sheet why-malaysia-thailand
A1: Column1 | B1: Column2
A2: Page URL: | B2: https://tpmyandtpth.github.io/MLP/why-malaysia-thailand.html
A3: Page Title (Local): | B3: "像local一样，overseas工作。"
A4: Page Title (Expat): | B4: "像本地人一样，在海外工作。"
A5: Extraction Date: | B5: 2026-01-27
A6: Review Status: | B6: ⬜ Pending
A7: Total Items: | B7: 68
A8: Line # | B8: Section | C8: Local Mandarin (Mixed English) | D8: Local Comment | E8: Native Mandarin | F8: Native Comment
A9: 1 | B9: City Info | C9: City的便利 × 多文化 × 华语Support | D9: =IFERROR(_xlfn.XLOOKUP(C9,index.html!C:C,index.html!D:D)," ") | E9: 城市的便利 × 多文化 × 华语支持
A10: 2 | B10: City Info | C10: MRT/Monorail/Grab移动很comfortable。通勤stress很少。 | D10: =IFERROR(_xlfn.XLOOKUP(C10,index.html!C:C,index.html!D:D)," ") | E10: MRT/单轨/Grab移动很舒适。通勤压力很少。
A11: 3 | B11: Content | C11: Don Quijote / AEON / ISETAN / 中餐厅很多。 | D11: =IFERROR(_xlfn.XLOOKUP(C11,index.html!C:C,index.html!D:D)," ") | E11: 唐吉诃德 / 永旺 / 伊势丹 / 中餐厅很多。
A12: 4 | B12: Content | C12: 华语service的hospital、华人学校、华人会都很complete。 | D12: =IFERROR(_xlfn.XLOOKUP(C12,index.html!C:C,index.html!D:D)," ") | E12: 华语服务的医院、华人学校、华人会都很完善。
A13: 5 | B13: Content | C13: Popular area（Mont Kiara / KLCC）的condominium设备豪华，rent比China便宜。 | D13: =IFERROR(_xlfn.XLOOKUP(C13,index.html!C:C,index.html!D:D)," ") | E13: 热门区域（满家乐 / 双子塔）的公寓设备豪华，租金比中国便宜。
A14: 6 | B14: Content | C14: 从KLIA到China（北京·上海·广州·深圳）和Asia各city有很多direct flight。 | D14: =IFERROR(_xlfn.XLOOKUP(C14,index.html!C:C,index.html!D:D)," ") | E14: 从吉隆坡国际机场到中国（北京·上海·广州·深圳）和亚洲各城市有很多直飞航班。
A15: 7 | B15: City Info | C15: 不想compromise city的便利/overseas life有不安、想要接近China的生活的人。 | D15: =IFERROR(_xlfn.XLOOKUP(C15,index.html!C:C,index.html!D:D)," ") | E15: 不想妥协城市的便利/海外生活有不安、想要接近中国的生活的人。
A16: 8 | B16: City Info | C16: Malaysia·Penang（槟城） | D16: =IFERROR(_xlfn.XLOOKUP(C16,index.html!C:C,index.html!D:D)," ") | E16: 马来西亚·槟城（Penang）
A17: 9 | B17: City Info | C17: Nature × History × 安静的Island Life | D17: =IFERROR(_xlfn.XLOOKUP(C17,index.html!C:C,index.html!D:D)," ") | E17: 自然 × 历史 × 安静的岛屿生活
A18: 10 | B18: City Info | C18: World Heritage的George Town。Cafe和街walk很enjoyable。 | D18: =IFERROR(_xlfn.XLOOKUP(C18,index.html!C:C,index.html!D:D)," ") | E18: 世界遗产的乔治城。咖啡馆和街头漫步很愉快。
A19: 11 | B19: Content | C19: 靠近海，view好的property很多，生活费比KL稍微cheap一点。 | D19: =IFERROR(_xlfn.XLOOKUP(C19,index.html!C:C,index.html!D:D)," ") | E19: 靠近海，景观好的房产很多，生活费比吉隆坡稍微便宜一点。
A20: 12 | B20: Content | C20: 华语medical和翻译service也有，long stay很popular。 | D20: =IFERROR(_xlfn.XLOOKUP(C20,index.html!C:C,index.html!D:D)," ") | E20: 华语医疗和翻译服务也有，长期居住很受欢迎。
... A76: 68 | B76: Section | C76: Apply Now | D76: =IFERROR(_xlfn.XLOOKUP(C76,index.html!C:C,index.html!D:D)," ") -> 立即申请 | E76: 立即申请
